<?xml version="1.0" encoding="UTF-8"?>
<Workbook xmlns="urn:schemas-microsoft-com:office:spreadsheet" xmlns:x="urn:schemas-microsoft-com:office:excel" xmlns:ss="urn:schemas-microsoft-com:office:spreadsheet">
   <Worksheet ss:Name="Ark1">
      <Table x:FullColumns="1" x:FullRows="1">
         <Row>
            <Cell>
               <Data ss:Type="String">Correspondence</Data>
            </Cell>
            <Cell>
               <Data ss:Type="String">Relation</Data>
            </Cell>
            <Cell>
               <Data ss:Type="String">Measure</Data>
            </Cell>
         </Row>
         <Row>
            <Cell>
               <Data ss:Type="String">CodeAirportHeliportCollocationType - CodeAerodromeCollocationType</Data>
            </Cell>
            <Cell>
               <Data ss:Type="String">=</Data>
            </Cell>
            <Cell>
               <Data ss:Type="String">0.9085812021386745</Data>
            </Cell>
         </Row>
         <Row>
            <Cell>
               <Data ss:Type="String">Marking - MarkingElement</Data>
            </Cell>
            <Cell>
               <Data ss:Type="String">=</Data>
            </Cell>
            <Cell>
               <Data ss:Type="String">0.9497757517109753</Data>
            </Cell>
         </Row>
         <Row>
            <Cell>
               <Data ss:Type="String">AirportHeliportContamination - AircraftStandContamination</Data>
            </Cell>
            <Cell>
               <Data ss:Type="String">=</Data>
            </Cell>
            <Cell>
               <Data ss:Type="String">0.9265745722260426</Data>
            </Cell>
         </Row>
         <Row>
            <Cell>
               <Data ss:Type="String">AirportHeliportContamination - TouchDownLiftOffContamination</Data>
            </Cell>
            <Cell>
               <Data ss:Type="String">=</Data>
            </Cell>
            <Cell>
               <Data ss:Type="String">0.9336919490765645</Data>
            </Cell>
         </Row>
         <Row>
            <Cell>
               <Data ss:Type="String">AirportHeliportContamination - ApronContamination</Data>
            </Cell>
            <Cell>
               <Data ss:Type="String">=</Data>
            </Cell>
            <Cell>
               <Data ss:Type="String">0.9785969853328238</Data>
            </Cell>
         </Row>
         <Row>
            <Cell>
               <Data ss:Type="String">AirportHeliportContamination - AerodromeContamination</Data>
            </Cell>
            <Cell>
               <Data ss:Type="String">=</Data>
            </Cell>
            <Cell>
               <Data ss:Type="String">0.9598995438470607</Data>
            </Cell>
         </Row>
         <Row>
            <Cell>
               <Data ss:Type="String">AirportHeliportContamination - RunwayContamination</Data>
            </Cell>
            <Cell>
               <Data ss:Type="String">=</Data>
            </Cell>
            <Cell>
               <Data ss:Type="String">0.971815935189609</Data>
            </Cell>
         </Row>
         <Row>
            <Cell>
               <Data ss:Type="String">AirportHeliportContamination - TaxiwayContamination</Data>
            </Cell>
            <Cell>
               <Data ss:Type="String">=</Data>
            </Cell>
            <Cell>
               <Data ss:Type="String">0.9695975729971997</Data>
            </Cell>
         </Row>
         <Row>
            <Cell>
               <Data ss:Type="String">AirportHeliportContamination - RunwaySectionContamination</Data>
            </Cell>
            <Cell>
               <Data ss:Type="String">=</Data>
            </Cell>
            <Cell>
               <Data ss:Type="String">0.9512623521147487</Data>
            </Cell>
         </Row>
         <Row>
            <Cell>
               <Data ss:Type="String">CodeLightHoldingPositionType - CodeLightHoldingPositionType</Data>
            </Cell>
            <Cell>
               <Data ss:Type="String">=</Data>
            </Cell>
            <Cell>
               <Data ss:Type="String">1.0</Data>
            </Cell>
         </Row>
         <Row>
            <Cell>
               <Data ss:Type="String">CodeRunwaySectionType - CodeTaxiwaySectionType</Data>
            </Cell>
            <Cell>
               <Data ss:Type="String">=</Data>
            </Cell>
            <Cell>
               <Data ss:Type="String">0.9627512699448517</Data>
            </Cell>
         </Row>
         <Row>
            <Cell>
               <Data ss:Type="String">CodeRunwaySectionType - CodeSurfaceCompositionType</Data>
            </Cell>
            <Cell>
               <Data ss:Type="String">=</Data>
            </Cell>
            <Cell>
               <Data ss:Type="String">0.9183161228374577</Data>
            </Cell>
         </Row>
         <Row>
            <Cell>
               <Data ss:Type="String">CodeRunwaySectionType - CodeRunwaySectionType</Data>
            </Cell>
            <Cell>
               <Data ss:Type="String">=</Data>
            </Cell>
            <Cell>
               <Data ss:Type="String">1.0</Data>
            </Cell>
         </Row>
         <Row>
            <Cell>
               <Data ss:Type="String">CodeMilitaryOperationsType - CodeMilitaryOperationsType</Data>
            </Cell>
            <Cell>
               <Data ss:Type="String">=</Data>
            </Cell>
            <Cell>
               <Data ss:Type="String">1.0</Data>
            </Cell>
         </Row>
         <Row>
            <Cell>
               <Data ss:Type="String">CodeOperationManoeuvringAreaType - CodeOperationManoeuvringAreaType</Data>
            </Cell>
            <Cell>
               <Data ss:Type="String">=</Data>
            </Cell>
            <Cell>
               <Data ss:Type="String">0.9471629514078539</Data>
            </Cell>
         </Row>
         <Row>
            <Cell>
               <Data ss:Type="String">AirportHeliport - Aerodrome</Data>
            </Cell>
            <Cell>
               <Data ss:Type="String">=</Data>
            </Cell>
            <Cell>
               <Data ss:Type="String">0.9892215568862275</Data>
            </Cell>
         </Row>
         <Row>
            <Cell>
               <Data ss:Type="String">GuidanceLineMarking - GuidanceLineMarking</Data>
            </Cell>
            <Cell>
               <Data ss:Type="String">=</Data>
            </Cell>
            <Cell>
               <Data ss:Type="String">1.0</Data>
            </Cell>
         </Row>
         <Row>
            <Cell>
               <Data ss:Type="String">CodeGradeSeparationType - CodeGradeSeparationType</Data>
            </Cell>
            <Cell>
               <Data ss:Type="String">=</Data>
            </Cell>
            <Cell>
               <Data ss:Type="String">1.0</Data>
            </Cell>
         </Row>
         <Row>
            <Cell>
               <Data ss:Type="String">CodeMarkingConditionType - CodeMarkingConditionType</Data>
            </Cell>
            <Cell>
               <Data ss:Type="String">=</Data>
            </Cell>
            <Cell>
               <Data ss:Type="String">1.0</Data>
            </Cell>
         </Row>
         <Row>
            <Cell>
               <Data ss:Type="String">ApronMarking - RunwayMarking</Data>
            </Cell>
            <Cell>
               <Data ss:Type="String">=</Data>
            </Cell>
            <Cell>
               <Data ss:Type="String">0.9018398629373585</Data>
            </Cell>
         </Row>
         <Row>
            <Cell>
               <Data ss:Type="String">ApronMarking - ApronMarking</Data>
            </Cell>
            <Cell>
               <Data ss:Type="String">=</Data>
            </Cell>
            <Cell>
               <Data ss:Type="String">0.9460841654778888</Data>
            </Cell>
         </Row>
         <Row>
            <Cell>
               <Data ss:Type="String">ApronMarking - TaxiwayMarking</Data>
            </Cell>
            <Cell>
               <Data ss:Type="String">=</Data>
            </Cell>
            <Cell>
               <Data ss:Type="String">0.9587924016282225</Data>
            </Cell>
         </Row>
         <Row>
            <Cell>
               <Data ss:Type="String">ApronMarking - StandMarking</Data>
            </Cell>
            <Cell>
               <Data ss:Type="String">=</Data>
            </Cell>
            <Cell>
               <Data ss:Type="String">0.9483992245785113</Data>
            </Cell>
         </Row>
         <Row>
            <Cell>
               <Data ss:Type="String">ApronMarking - DeicingAreaMarking</Data>
            </Cell>
            <Cell>
               <Data ss:Type="String">=</Data>
            </Cell>
            <Cell>
               <Data ss:Type="String">0.9254275213760688</Data>
            </Cell>
         </Row>
         <Row>
            <Cell>
               <Data ss:Type="String">CodeRunwayMarkingType - CodeRunwayMarkingType</Data>
            </Cell>
            <Cell>
               <Data ss:Type="String">=</Data>
            </Cell>
            <Cell>
               <Data ss:Type="String">1.0</Data>
            </Cell>
         </Row>
         <Row>
            <Cell>
               <Data ss:Type="String">CodeApproachLightingICAOType - CodeApproachLightingICAOType</Data>
            </Cell>
            <Cell>
               <Data ss:Type="String">=</Data>
            </Cell>
            <Cell>
               <Data ss:Type="String">1.0</Data>
            </Cell>
         </Row>
         <Row>
            <Cell>
               <Data ss:Type="String">DeicingAreaMarking - DeicingAreaMarking</Data>
            </Cell>
            <Cell>
               <Data ss:Type="String">=</Data>
            </Cell>
            <Cell>
               <Data ss:Type="String">1.0</Data>
            </Cell>
         </Row>
         <Row>
            <Cell>
               <Data ss:Type="String">DeicingAreaMarking - TaxiwayMarking</Data>
            </Cell>
            <Cell>
               <Data ss:Type="String">=</Data>
            </Cell>
            <Cell>
               <Data ss:Type="String">0.9171219187208528</Data>
            </Cell>
         </Row>
         <Row>
            <Cell>
               <Data ss:Type="String">GuidanceLine - GuidanceLine</Data>
            </Cell>
            <Cell>
               <Data ss:Type="String">=</Data>
            </Cell>
            <Cell>
               <Data ss:Type="String">1.0</Data>
            </Cell>
         </Row>
         <Row>
            <Cell>
               <Data ss:Type="String">ManoeuvringAreaUsage - ManoeuvringAreaUsage</Data>
            </Cell>
            <Cell>
               <Data ss:Type="String">=</Data>
            </Cell>
            <Cell>
               <Data ss:Type="String">1.0</Data>
            </Cell>
         </Row>
         <Row>
            <Cell>
               <Data ss:Type="String">ApronContamination - RunwayContamination</Data>
            </Cell>
            <Cell>
               <Data ss:Type="String">=</Data>
            </Cell>
            <Cell>
               <Data ss:Type="String">0.9781225607511046</Data>
            </Cell>
         </Row>
         <Row>
            <Cell>
               <Data ss:Type="String">ApronContamination - TouchDownLiftOffContamination</Data>
            </Cell>
            <Cell>
               <Data ss:Type="String">=</Data>
            </Cell>
            <Cell>
               <Data ss:Type="String">0.9426154580240229</Data>
            </Cell>
         </Row>
         <Row>
            <Cell>
               <Data ss:Type="String">ApronContamination - AerodromeContamination</Data>
            </Cell>
            <Cell>
               <Data ss:Type="String">=</Data>
            </Cell>
            <Cell>
               <Data ss:Type="String">0.9616941967611925</Data>
            </Cell>
         </Row>
         <Row>
            <Cell>
               <Data ss:Type="String">ApronContamination - RunwaySectionContamination</Data>
            </Cell>
            <Cell>
               <Data ss:Type="String">=</Data>
            </Cell>
            <Cell>
               <Data ss:Type="String">0.9590924060926117</Data>
            </Cell>
         </Row>
         <Row>
            <Cell>
               <Data ss:Type="String">ApronContamination - ApronContamination</Data>
            </Cell>
            <Cell>
               <Data ss:Type="String">=</Data>
            </Cell>
            <Cell>
               <Data ss:Type="String">1.0</Data>
            </Cell>
         </Row>
         <Row>
            <Cell>
               <Data ss:Type="String">ApronContamination - AircraftStandContamination</Data>
            </Cell>
            <Cell>
               <Data ss:Type="String">=</Data>
            </Cell>
            <Cell>
               <Data ss:Type="String">0.9156171424004524</Data>
            </Cell>
         </Row>
         <Row>
            <Cell>
               <Data ss:Type="String">ApronContamination - TaxiwayContamination</Data>
            </Cell>
            <Cell>
               <Data ss:Type="String">=</Data>
            </Cell>
            <Cell>
               <Data ss:Type="String">0.9760824395456524</Data>
            </Cell>
         </Row>
         <Row>
            <Cell>
               <Data ss:Type="String">AircraftStandContamination - ApronContamination</Data>
            </Cell>
            <Cell>
               <Data ss:Type="String">=</Data>
            </Cell>
            <Cell>
               <Data ss:Type="String">0.9156171424004524</Data>
            </Cell>
         </Row>
         <Row>
            <Cell>
               <Data ss:Type="String">AircraftStandContamination - AerodromeContamination</Data>
            </Cell>
            <Cell>
               <Data ss:Type="String">=</Data>
            </Cell>
            <Cell>
               <Data ss:Type="String">0.9107096819832424</Data>
            </Cell>
         </Row>
         <Row>
            <Cell>
               <Data ss:Type="String">AircraftStandContamination - AircraftStandContamination</Data>
            </Cell>
            <Cell>
               <Data ss:Type="String">=</Data>
            </Cell>
            <Cell>
               <Data ss:Type="String">1.0</Data>
            </Cell>
         </Row>
         <Row>
            <Cell>
               <Data ss:Type="String">AircraftStandContamination - TaxiwayContamination</Data>
            </Cell>
            <Cell>
               <Data ss:Type="String">=</Data>
            </Cell>
            <Cell>
               <Data ss:Type="String">0.9107096819832424</Data>
            </Cell>
         </Row>
         <Row>
            <Cell>
               <Data ss:Type="String">AircraftStandContamination - RunwayContamination</Data>
            </Cell>
            <Cell>
               <Data ss:Type="String">=</Data>
            </Cell>
            <Cell>
               <Data ss:Type="String">0.9131390449438201</Data>
            </Cell>
         </Row>
         <Row>
            <Cell>
               <Data ss:Type="String">AirportHotSpot - AerodromeHotSpot</Data>
            </Cell>
            <Cell>
               <Data ss:Type="String">=</Data>
            </Cell>
            <Cell>
               <Data ss:Type="String">0.9979020979020978</Data>
            </Cell>
         </Row>
         <Row>
            <Cell>
               <Data ss:Type="String">TaxiHoldingPosition - TaxiwayIntersectionMarking</Data>
            </Cell>
            <Cell>
               <Data ss:Type="String">=</Data>
            </Cell>
            <Cell>
               <Data ss:Type="String">0.904985201627821</Data>
            </Cell>
         </Row>
         <Row>
            <Cell>
               <Data ss:Type="String">CodeRunwayProtectionAreaType - CodeRunwayProtectionAreaType</Data>
            </Cell>
            <Cell>
               <Data ss:Type="String">=</Data>
            </Cell>
            <Cell>
               <Data ss:Type="String">1.0</Data>
            </Cell>
         </Row>
         <Row>
            <Cell>
               <Data ss:Type="String">DeicingArea - DeicingArea</Data>
            </Cell>
            <Cell>
               <Data ss:Type="String">=</Data>
            </Cell>
            <Cell>
               <Data ss:Type="String">0.9576515640006873</Data>
            </Cell>
         </Row>
         <Row>
            <Cell>
               <Data ss:Type="String">TaxiwayMarking - TaxiwayHoldingPositionMarking</Data>
            </Cell>
            <Cell>
               <Data ss:Type="String">=</Data>
            </Cell>
            <Cell>
               <Data ss:Type="String">0.9126582278481012</Data>
            </Cell>
         </Row>
         <Row>
            <Cell>
               <Data ss:Type="String">TaxiwayMarking - DeicingAreaMarking</Data>
            </Cell>
            <Cell>
               <Data ss:Type="String">=</Data>
            </Cell>
            <Cell>
               <Data ss:Type="String">0.9171219187208528</Data>
            </Cell>
         </Row>
         <Row>
            <Cell>
               <Data ss:Type="String">TaxiwayMarking - StandMarking</Data>
            </Cell>
            <Cell>
               <Data ss:Type="String">=</Data>
            </Cell>
            <Cell>
               <Data ss:Type="String">0.9310366003438959</Data>
            </Cell>
         </Row>
         <Row>
            <Cell>
               <Data ss:Type="String">TaxiwayMarking - TaxiwayMarking</Data>
            </Cell>
            <Cell>
               <Data ss:Type="String">=</Data>
            </Cell>
            <Cell>
               <Data ss:Type="String">1.0</Data>
            </Cell>
         </Row>
         <Row>
            <Cell>
               <Data ss:Type="String">CodePCNMethodType - CodePCNMethodType</Data>
            </Cell>
            <Cell>
               <Data ss:Type="String">=</Data>
            </Cell>
            <Cell>
               <Data ss:Type="String">1.0</Data>
            </Cell>
         </Row>
         <Row>
            <Cell>
               <Data ss:Type="String">CodeUsageLimitationType - CodeUsageLimitationType</Data>
            </Cell>
            <Cell>
               <Data ss:Type="String">=</Data>
            </Cell>
            <Cell>
               <Data ss:Type="String">1.0</Data>
            </Cell>
         </Row>
         <Row>
            <Cell>
               <Data ss:Type="String">ApproachLightingSystem - ApproachLightingSystem</Data>
            </Cell>
            <Cell>
               <Data ss:Type="String">=</Data>
            </Cell>
            <Cell>
               <Data ss:Type="String">1.0</Data>
            </Cell>
         </Row>
         <Row>
            <Cell>
               <Data ss:Type="String">CodeApronElementType - CodeRoadType</Data>
            </Cell>
            <Cell>
               <Data ss:Type="String">=</Data>
            </Cell>
            <Cell>
               <Data ss:Type="String">0.9450843106365598</Data>
            </Cell>
         </Row>
         <Row>
            <Cell>
               <Data ss:Type="String">CodeApronElementType - CodeAircraftStandType</Data>
            </Cell>
            <Cell>
               <Data ss:Type="String">=</Data>
            </Cell>
            <Cell>
               <Data ss:Type="String">0.9278041948563878</Data>
            </Cell>
         </Row>
         <Row>
            <Cell>
               <Data ss:Type="String">CodeVisualDockingGuidanceType - CodeVisualDockingGuidanceType</Data>
            </Cell>
            <Cell>
               <Data ss:Type="String">=</Data>
            </Cell>
            <Cell>
               <Data ss:Type="String">1.0</Data>
            </Cell>
         </Row>
         <Row>
            <Cell>
               <Data ss:Type="String">RunwayVisualRange - RunwayVisualRange</Data>
            </Cell>
            <Cell>
               <Data ss:Type="String">=</Data>
            </Cell>
            <Cell>
               <Data ss:Type="String">0.9085362695642266</Data>
            </Cell>
         </Row>
         <Row>
            <Cell>
               <Data ss:Type="String">CodePCNPavementType - CodePCNPavementType</Data>
            </Cell>
            <Cell>
               <Data ss:Type="String">=</Data>
            </Cell>
            <Cell>
               <Data ss:Type="String">1.0</Data>
            </Cell>
         </Row>
         <Row>
            <Cell>
               <Data ss:Type="String">CodeRunwayType - CodeRunwayType</Data>
            </Cell>
            <Cell>
               <Data ss:Type="String">=</Data>
            </Cell>
            <Cell>
               <Data ss:Type="String">1.0</Data>
            </Cell>
         </Row>
         <Row>
            <Cell>
               <Data ss:Type="String">RunwayProtectAreaLightSystem - RunwayProtectAreaLightSystem</Data>
            </Cell>
            <Cell>
               <Data ss:Type="String">=</Data>
            </Cell>
            <Cell>
               <Data ss:Type="String">0.9904824117320443</Data>
            </Cell>
         </Row>
         <Row>
            <Cell>
               <Data ss:Type="String">ApronAreaUsage - ApronAreaUsage</Data>
            </Cell>
            <Cell>
               <Data ss:Type="String">=</Data>
            </Cell>
            <Cell>
               <Data ss:Type="String">1.0</Data>
            </Cell>
         </Row>
         <Row>
            <Cell>
               <Data ss:Type="String">CodeDirectionType - CodeDirectionType</Data>
            </Cell>
            <Cell>
               <Data ss:Type="String">=</Data>
            </Cell>
            <Cell>
               <Data ss:Type="String">1.0</Data>
            </Cell>
         </Row>
         <Row>
            <Cell>
               <Data ss:Type="String">CodeAircraftStandType - CodeRoadType</Data>
            </Cell>
            <Cell>
               <Data ss:Type="String">=</Data>
            </Cell>
            <Cell>
               <Data ss:Type="String">0.9278041948563878</Data>
            </Cell>
         </Row>
         <Row>
            <Cell>
               <Data ss:Type="String">CodeAircraftStandType - CodeAircraftStandType</Data>
            </Cell>
            <Cell>
               <Data ss:Type="String">=</Data>
            </Cell>
            <Cell>
               <Data ss:Type="String">1.0</Data>
            </Cell>
         </Row>
         <Row>
            <Cell>
               <Data ss:Type="String">RunwayProtectArea - RunwayProtectArea</Data>
            </Cell>
            <Cell>
               <Data ss:Type="String">=</Data>
            </Cell>
            <Cell>
               <Data ss:Type="String">1.0</Data>
            </Cell>
         </Row>
         <Row>
            <Cell>
               <Data ss:Type="String">RunwayProtectArea - AerodromeProtectionArea</Data>
            </Cell>
            <Cell>
               <Data ss:Type="String">=</Data>
            </Cell>
            <Cell>
               <Data ss:Type="String">0.9286713286713286</Data>
            </Cell>
         </Row>
         <Row>
            <Cell>
               <Data ss:Type="String">CodeMarkingStyleType - CodeMarkingStyleType</Data>
            </Cell>
            <Cell>
               <Data ss:Type="String">=</Data>
            </Cell>
            <Cell>
               <Data ss:Type="String">1.0</Data>
            </Cell>
         </Row>
         <Row>
            <Cell>
               <Data ss:Type="String">NonMovementArea - NonMovementArea</Data>
            </Cell>
            <Cell>
               <Data ss:Type="String">=</Data>
            </Cell>
            <Cell>
               <Data ss:Type="String">1.0</Data>
            </Cell>
         </Row>
         <Row>
            <Cell>
               <Data ss:Type="String">CodeRunwayElementType - CodeTaxiwayType</Data>
            </Cell>
            <Cell>
               <Data ss:Type="String">=</Data>
            </Cell>
            <Cell>
               <Data ss:Type="String">0.9151799294394355</Data>
            </Cell>
         </Row>
         <Row>
            <Cell>
               <Data ss:Type="String">CodeRunwayElementType - CodeRunwayElementType</Data>
            </Cell>
            <Cell>
               <Data ss:Type="String">=</Data>
            </Cell>
            <Cell>
               <Data ss:Type="String">0.9674698795180723</Data>
            </Cell>
         </Row>
         <Row>
            <Cell>
               <Data ss:Type="String">CodeBuoyType - CodeBuoyType</Data>
            </Cell>
            <Cell>
               <Data ss:Type="String">=</Data>
            </Cell>
            <Cell>
               <Data ss:Type="String">1.0</Data>
            </Cell>
         </Row>
         <Row>
            <Cell>
               <Data ss:Type="String">CodeLightIntensityType - CodeLightIntensityType</Data>
            </Cell>
            <Cell>
               <Data ss:Type="String">=</Data>
            </Cell>
            <Cell>
               <Data ss:Type="String">1.0</Data>
            </Cell>
         </Row>
         <Row>
            <Cell>
               <Data ss:Type="String">RunwayDeclaredDistance - RunwayDeclaredDistance</Data>
            </Cell>
            <Cell>
               <Data ss:Type="String">=</Data>
            </Cell>
            <Cell>
               <Data ss:Type="String">1.0</Data>
            </Cell>
         </Row>
         <Row>
            <Cell>
               <Data ss:Type="String">CodeLightingJARType - CodeLightingJARType</Data>
            </Cell>
            <Cell>
               <Data ss:Type="String">=</Data>
            </Cell>
            <Cell>
               <Data ss:Type="String">1.0</Data>
            </Cell>
         </Row>
         <Row>
            <Cell>
               <Data ss:Type="String">ArrestingGear - ArrestingGear</Data>
            </Cell>
            <Cell>
               <Data ss:Type="String">=</Data>
            </Cell>
            <Cell>
               <Data ss:Type="String">0.965137988516392</Data>
            </Cell>
         </Row>
         <Row>
            <Cell>
               <Data ss:Type="String">CodeWorkAreaType - CodeWorkAreaType</Data>
            </Cell>
            <Cell>
               <Data ss:Type="String">=</Data>
            </Cell>
            <Cell>
               <Data ss:Type="String">1.0</Data>
            </Cell>
         </Row>
         <Row>
            <Cell>
               <Data ss:Type="String">CodeSurfaceCompositionType - CodeRunwaySectionType</Data>
            </Cell>
            <Cell>
               <Data ss:Type="String">=</Data>
            </Cell>
            <Cell>
               <Data ss:Type="String">0.9183161228374577</Data>
            </Cell>
         </Row>
         <Row>
            <Cell>
               <Data ss:Type="String">CodeSurfaceCompositionType - CodeSurfaceCompositionType</Data>
            </Cell>
            <Cell>
               <Data ss:Type="String">=</Data>
            </Cell>
            <Cell>
               <Data ss:Type="String">1.0</Data>
            </Cell>
         </Row>
         <Row>
            <Cell>
               <Data ss:Type="String">CodeSurfaceCompositionType - CodeTaxiwaySectionType</Data>
            </Cell>
            <Cell>
               <Data ss:Type="String">=</Data>
            </Cell>
            <Cell>
               <Data ss:Type="String">0.90935689367511</Data>
            </Cell>
         </Row>
         <Row>
            <Cell>
               <Data ss:Type="String">CodeTLOFSectionType - CodeTaxiwaySectionType</Data>
            </Cell>
            <Cell>
               <Data ss:Type="String">=</Data>
            </Cell>
            <Cell>
               <Data ss:Type="String">0.9102135799493916</Data>
            </Cell>
         </Row>
         <Row>
            <Cell>
               <Data ss:Type="String">CodeTLOFSectionType - CodeTLOFSectionType</Data>
            </Cell>
            <Cell>
               <Data ss:Type="String">=</Data>
            </Cell>
            <Cell>
               <Data ss:Type="String">1.0</Data>
            </Cell>
         </Row>
         <Row>
            <Cell>
               <Data ss:Type="String">CodeAuthorityRoleType - CodeAuthorityRoleType</Data>
            </Cell>
            <Cell>
               <Data ss:Type="String">=</Data>
            </Cell>
            <Cell>
               <Data ss:Type="String">1.0</Data>
            </Cell>
         </Row>
         <Row>
            <Cell>
               <Data ss:Type="String">CodeSurfaceConditionType - CodeSurfaceConditionType</Data>
            </Cell>
            <Cell>
               <Data ss:Type="String">=</Data>
            </Cell>
            <Cell>
               <Data ss:Type="String">1.0</Data>
            </Cell>
         </Row>
         <Row>
            <Cell>
               <Data ss:Type="String">RunwayBlastPad - RunwayBlastPad</Data>
            </Cell>
            <Cell>
               <Data ss:Type="String">=</Data>
            </Cell>
            <Cell>
               <Data ss:Type="String">0.9969985734571314</Data>
            </Cell>
         </Row>
         <Row>
            <Cell>
               <Data ss:Type="String">CodeOperationAirportHeliportType - CodeOperationAerodromeType</Data>
            </Cell>
            <Cell>
               <Data ss:Type="String">=</Data>
            </Cell>
            <Cell>
               <Data ss:Type="String">0.9479019225564106</Data>
            </Cell>
         </Row>
         <Row>
            <Cell>
               <Data ss:Type="String">TouchDownLiftOff - TouchDownLiftOff</Data>
            </Cell>
            <Cell>
               <Data ss:Type="String">=</Data>
            </Cell>
            <Cell>
               <Data ss:Type="String">0.9972972972972973</Data>
            </Cell>
         </Row>
         <Row>
            <Cell>
               <Data ss:Type="String">RunwayContamination - ApronContamination</Data>
            </Cell>
            <Cell>
               <Data ss:Type="String">=</Data>
            </Cell>
            <Cell>
               <Data ss:Type="String">0.9781225607511046</Data>
            </Cell>
         </Row>
         <Row>
            <Cell>
               <Data ss:Type="String">RunwayContamination - RunwaySectionContamination</Data>
            </Cell>
            <Cell>
               <Data ss:Type="String">=</Data>
            </Cell>
            <Cell>
               <Data ss:Type="String">0.9838709677419355</Data>
            </Cell>
         </Row>
         <Row>
            <Cell>
               <Data ss:Type="String">RunwayContamination - RunwayContamination</Data>
            </Cell>
            <Cell>
               <Data ss:Type="String">=</Data>
            </Cell>
            <Cell>
               <Data ss:Type="String">1.0</Data>
            </Cell>
         </Row>
         <Row>
            <Cell>
               <Data ss:Type="String">RunwayContamination - TaxiwayContamination</Data>
            </Cell>
            <Cell>
               <Data ss:Type="String">=</Data>
            </Cell>
            <Cell>
               <Data ss:Type="String">0.9869215098532811</Data>
            </Cell>
         </Row>
         <Row>
            <Cell>
               <Data ss:Type="String">RunwayContamination - AerodromeContamination</Data>
            </Cell>
            <Cell>
               <Data ss:Type="String">=</Data>
            </Cell>
            <Cell>
               <Data ss:Type="String">0.9593626945836156</Data>
            </Cell>
         </Row>
         <Row>
            <Cell>
               <Data ss:Type="String">RunwayContamination - TouchDownLiftOffContamination</Data>
            </Cell>
            <Cell>
               <Data ss:Type="String">=</Data>
            </Cell>
            <Cell>
               <Data ss:Type="String">0.939574059255071</Data>
            </Cell>
         </Row>
         <Row>
            <Cell>
               <Data ss:Type="String">RunwayContamination - AircraftStandContamination</Data>
            </Cell>
            <Cell>
               <Data ss:Type="String">=</Data>
            </Cell>
            <Cell>
               <Data ss:Type="String">0.9131390449438201</Data>
            </Cell>
         </Row>
         <Row>
            <Cell>
               <Data ss:Type="String">CodeStatusOperationsType - CodeStatusOperationsType</Data>
            </Cell>
            <Cell>
               <Data ss:Type="String">=</Data>
            </Cell>
            <Cell>
               <Data ss:Type="String">1.0</Data>
            </Cell>
         </Row>
         <Row>
            <Cell>
               <Data ss:Type="String">CodeTaxiwayType - CodeTaxiwayType</Data>
            </Cell>
            <Cell>
               <Data ss:Type="String">=</Data>
            </Cell>
            <Cell>
               <Data ss:Type="String">1.0</Data>
            </Cell>
         </Row>
         <Row>
            <Cell>
               <Data ss:Type="String">SurfaceContamination - SurfaceContamination</Data>
            </Cell>
            <Cell>
               <Data ss:Type="String">=</Data>
            </Cell>
            <Cell>
               <Data ss:Type="String">0.9836363636363636</Data>
            </Cell>
         </Row>
         <Row>
            <Cell>
               <Data ss:Type="String">TouchDownLiftOffMarking - DeicingAreaMarking</Data>
            </Cell>
            <Cell>
               <Data ss:Type="String">=</Data>
            </Cell>
            <Cell>
               <Data ss:Type="String">0.9005598908543293</Data>
            </Cell>
         </Row>
         <Row>
            <Cell>
               <Data ss:Type="String">TouchDownLiftOffMarking - TouchDownLiftOffMarking</Data>
            </Cell>
            <Cell>
               <Data ss:Type="String">=</Data>
            </Cell>
            <Cell>
               <Data ss:Type="String">0.9754716981132076</Data>
            </Cell>
         </Row>
         <Row>
            <Cell>
               <Data ss:Type="String">TouchDownLiftOffMarking - TaxiwayMarking</Data>
            </Cell>
            <Cell>
               <Data ss:Type="String">=</Data>
            </Cell>
            <Cell>
               <Data ss:Type="String">0.9102135799493916</Data>
            </Cell>
         </Row>
         <Row>
            <Cell>
               <Data ss:Type="String">TouchDownLiftOffMarking - StandMarking</Data>
            </Cell>
            <Cell>
               <Data ss:Type="String">=</Data>
            </Cell>
            <Cell>
               <Data ss:Type="String">0.9006268467980232</Data>
            </Cell>
         </Row>
         <Row>
            <Cell>
               <Data ss:Type="String">CodeStatusAirportType - CodeStatusAirportType</Data>
            </Cell>
            <Cell>
               <Data ss:Type="String">=</Data>
            </Cell>
            <Cell>
               <Data ss:Type="String">0.9554348962134016</Data>
            </Cell>
         </Row>
         <Row>
            <Cell>
               <Data ss:Type="String">CodeAirportHeliportType - CodeAerodromeType</Data>
            </Cell>
            <Cell>
               <Data ss:Type="String">=</Data>
            </Cell>
            <Cell>
               <Data ss:Type="String">0.9639624487069377</Data>
            </Cell>
         </Row>
         <Row>
            <Cell>
               <Data ss:Type="String">StandMarking - TaxiwayMarking</Data>
            </Cell>
            <Cell>
               <Data ss:Type="String">=</Data>
            </Cell>
            <Cell>
               <Data ss:Type="String">0.9310366003438959</Data>
            </Cell>
         </Row>
         <Row>
            <Cell>
               <Data ss:Type="String">StandMarking - StandMarking</Data>
            </Cell>
            <Cell>
               <Data ss:Type="String">=</Data>
            </Cell>
            <Cell>
               <Data ss:Type="String">1.0</Data>
            </Cell>
         </Row>
         <Row>
            <Cell>
               <Data ss:Type="String">AircraftStand - AircraftStand</Data>
            </Cell>
            <Cell>
               <Data ss:Type="String">=</Data>
            </Cell>
            <Cell>
               <Data ss:Type="String">1.0</Data>
            </Cell>
         </Row>
         <Row>
            <Cell>
               <Data ss:Type="String">CodeVerticalDatumType - CodeVerticalDatumType</Data>
            </Cell>
            <Cell>
               <Data ss:Type="String">=</Data>
            </Cell>
            <Cell>
               <Data ss:Type="String">1.0</Data>
            </Cell>
         </Row>
         <Row>
            <Cell>
               <Data ss:Type="String">Runway - Runway</Data>
            </Cell>
            <Cell>
               <Data ss:Type="String">=</Data>
            </Cell>
            <Cell>
               <Data ss:Type="String">0.9842105263157894</Data>
            </Cell>
         </Row>
         <Row>
            <Cell>
               <Data ss:Type="String">CodeArrestingGearEngageDeviceType - CodeArrestingGearEngageDeviceType</Data>
            </Cell>
            <Cell>
               <Data ss:Type="String">=</Data>
            </Cell>
            <Cell>
               <Data ss:Type="String">1.0</Data>
            </Cell>
         </Row>
         <Row>
            <Cell>
               <Data ss:Type="String">CodeDirectionTurnType - CodeDirectionTurnType</Data>
            </Cell>
            <Cell>
               <Data ss:Type="String">=</Data>
            </Cell>
            <Cell>
               <Data ss:Type="String">1.0</Data>
            </Cell>
         </Row>
         <Row>
            <Cell>
               <Data ss:Type="String">CodeGuidanceLineType - CodeGuidanceLineType</Data>
            </Cell>
            <Cell>
               <Data ss:Type="String">=</Data>
            </Cell>
            <Cell>
               <Data ss:Type="String">1.0</Data>
            </Cell>
         </Row>
         <Row>
            <Cell>
               <Data ss:Type="String">CodeRoadType - CodeAircraftStandType</Data>
            </Cell>
            <Cell>
               <Data ss:Type="String">=</Data>
            </Cell>
            <Cell>
               <Data ss:Type="String">0.9278041948563878</Data>
            </Cell>
         </Row>
         <Row>
            <Cell>
               <Data ss:Type="String">CodeRoadType - CodeRoadType</Data>
            </Cell>
            <Cell>
               <Data ss:Type="String">=</Data>
            </Cell>
            <Cell>
               <Data ss:Type="String">1.0</Data>
            </Cell>
         </Row>
         <Row>
            <Cell>
               <Data ss:Type="String">TaxiwayLightSystem - TaxiwayLightSystem</Data>
            </Cell>
            <Cell>
               <Data ss:Type="String">=</Data>
            </Cell>
            <Cell>
               <Data ss:Type="String">0.9747663551401868</Data>
            </Cell>
         </Row>
         <Row>
            <Cell>
               <Data ss:Type="String">CodeLoadingBridgeType - CodeLoadingBridgeType</Data>
            </Cell>
            <Cell>
               <Data ss:Type="String">=</Data>
            </Cell>
            <Cell>
               <Data ss:Type="String">1.0</Data>
            </Cell>
         </Row>
         <Row>
            <Cell>
               <Data ss:Type="String">TouchDownLiftOffLightSystem - TaxiwayLightSystem</Data>
            </Cell>
            <Cell>
               <Data ss:Type="String">=</Data>
            </Cell>
            <Cell>
               <Data ss:Type="String">0.907632571659721</Data>
            </Cell>
         </Row>
         <Row>
            <Cell>
               <Data ss:Type="String">TouchDownLiftOffLightSystem - TouchDownLiftOffLightSystem</Data>
            </Cell>
            <Cell>
               <Data ss:Type="String">=</Data>
            </Cell>
            <Cell>
               <Data ss:Type="String">0.9030095801809652</Data>
            </Cell>
         </Row>
         <Row>
            <Cell>
               <Data ss:Type="String">RunwaySectionContamination - AerodromeContamination</Data>
            </Cell>
            <Cell>
               <Data ss:Type="String">=</Data>
            </Cell>
            <Cell>
               <Data ss:Type="String">0.9435394092132736</Data>
            </Cell>
         </Row>
         <Row>
            <Cell>
               <Data ss:Type="String">RunwaySectionContamination - TouchDownLiftOffContamination</Data>
            </Cell>
            <Cell>
               <Data ss:Type="String">=</Data>
            </Cell>
            <Cell>
               <Data ss:Type="String">0.9124871606172349</Data>
            </Cell>
         </Row>
         <Row>
            <Cell>
               <Data ss:Type="String">RunwaySectionContamination - RunwaySectionContamination</Data>
            </Cell>
            <Cell>
               <Data ss:Type="String">=</Data>
            </Cell>
            <Cell>
               <Data ss:Type="String">1.0</Data>
            </Cell>
         </Row>
         <Row>
            <Cell>
               <Data ss:Type="String">RunwaySectionContamination - ApronContamination</Data>
            </Cell>
            <Cell>
               <Data ss:Type="String">=</Data>
            </Cell>
            <Cell>
               <Data ss:Type="String">0.9590924060926117</Data>
            </Cell>
         </Row>
         <Row>
            <Cell>
               <Data ss:Type="String">RunwaySectionContamination - TaxiwayContamination</Data>
            </Cell>
            <Cell>
               <Data ss:Type="String">=</Data>
            </Cell>
            <Cell>
               <Data ss:Type="String">0.9682691108617034</Data>
            </Cell>
         </Row>
         <Row>
            <Cell>
               <Data ss:Type="String">RunwaySectionContamination - RunwayContamination</Data>
            </Cell>
            <Cell>
               <Data ss:Type="String">=</Data>
            </Cell>
            <Cell>
               <Data ss:Type="String">0.9838709677419355</Data>
            </Cell>
         </Row>
         <Row>
            <Cell>
               <Data ss:Type="String">TouchDownLiftOffSafeArea - TouchDownLiftOffSafeArea</Data>
            </Cell>
            <Cell>
               <Data ss:Type="String">=</Data>
            </Cell>
            <Cell>
               <Data ss:Type="String">0.9947286350341908</Data>
            </Cell>
         </Row>
         <Row>
            <Cell>
               <Data ss:Type="String">AirportHeliportProtectionArea - RunwayProtectArea</Data>
            </Cell>
            <Cell>
               <Data ss:Type="String">=</Data>
            </Cell>
            <Cell>
               <Data ss:Type="String">0.9831168831168831</Data>
            </Cell>
         </Row>
         <Row>
            <Cell>
               <Data ss:Type="String">AirportHeliportProtectionArea - AerodromeProtectionArea</Data>
            </Cell>
            <Cell>
               <Data ss:Type="String">=</Data>
            </Cell>
            <Cell>
               <Data ss:Type="String">0.9372028271578496</Data>
            </Cell>
         </Row>
         <Row>
            <Cell>
               <Data ss:Type="String">CodeTaxiwaySectionType - CodeRunwaySectionType</Data>
            </Cell>
            <Cell>
               <Data ss:Type="String">=</Data>
            </Cell>
            <Cell>
               <Data ss:Type="String">0.9627512699448517</Data>
            </Cell>
         </Row>
         <Row>
            <Cell>
               <Data ss:Type="String">CodeTaxiwaySectionType - CodeTLOFSectionType</Data>
            </Cell>
            <Cell>
               <Data ss:Type="String">=</Data>
            </Cell>
            <Cell>
               <Data ss:Type="String">0.9102135799493916</Data>
            </Cell>
         </Row>
         <Row>
            <Cell>
               <Data ss:Type="String">CodeTaxiwaySectionType - CodeTaxiwaySectionType</Data>
            </Cell>
            <Cell>
               <Data ss:Type="String">=</Data>
            </Cell>
            <Cell>
               <Data ss:Type="String">1.0</Data>
            </Cell>
         </Row>
         <Row>
            <Cell>
               <Data ss:Type="String">CodeTaxiwaySectionType - CodeSurfaceCompositionType</Data>
            </Cell>
            <Cell>
               <Data ss:Type="String">=</Data>
            </Cell>
            <Cell>
               <Data ss:Type="String">0.90935689367511</Data>
            </Cell>
         </Row>
         <Row>
            <Cell>
               <Data ss:Type="String">SeaplaneRampSite - SeaplaneRampSite</Data>
            </Cell>
            <Cell>
               <Data ss:Type="String">=</Data>
            </Cell>
            <Cell>
               <Data ss:Type="String">1.0</Data>
            </Cell>
         </Row>
         <Row>
            <Cell>
               <Data ss:Type="String">FloatingDockSite - FloatingDockSite</Data>
            </Cell>
            <Cell>
               <Data ss:Type="String">=</Data>
            </Cell>
            <Cell>
               <Data ss:Type="String">1.0</Data>
            </Cell>
         </Row>
         <Row>
            <Cell>
               <Data ss:Type="String">VisualGlideSlopeIndicator - VisualGlideSlopeIndicator</Data>
            </Cell>
            <Cell>
               <Data ss:Type="String">=</Data>
            </Cell>
            <Cell>
               <Data ss:Type="String">0.9949062619845619</Data>
            </Cell>
         </Row>
         <Row>
            <Cell>
               <Data ss:Type="String">GroundLightSystem - GroundLightSystem</Data>
            </Cell>
            <Cell>
               <Data ss:Type="String">=</Data>
            </Cell>
            <Cell>
               <Data ss:Type="String">0.9951351351351352</Data>
            </Cell>
         </Row>
         <Row>
            <Cell>
               <Data ss:Type="String">RunwayMarking - TaxiwayMarking</Data>
            </Cell>
            <Cell>
               <Data ss:Type="String">=</Data>
            </Cell>
            <Cell>
               <Data ss:Type="String">0.9780786791595438</Data>
            </Cell>
         </Row>
         <Row>
            <Cell>
               <Data ss:Type="String">RunwayMarking - RunwayMarking</Data>
            </Cell>
            <Cell>
               <Data ss:Type="String">=</Data>
            </Cell>
            <Cell>
               <Data ss:Type="String">0.922972972972973</Data>
            </Cell>
         </Row>
         <Row>
            <Cell>
               <Data ss:Type="String">RunwayMarking - StandMarking</Data>
            </Cell>
            <Cell>
               <Data ss:Type="String">=</Data>
            </Cell>
            <Cell>
               <Data ss:Type="String">0.9353610845936123</Data>
            </Cell>
         </Row>
         <Row>
            <Cell>
               <Data ss:Type="String">RunwayMarking - DeicingAreaMarking</Data>
            </Cell>
            <Cell>
               <Data ss:Type="String">=</Data>
            </Cell>
            <Cell>
               <Data ss:Type="String">0.9212063129562416</Data>
            </Cell>
         </Row>
         <Row>
            <Cell>
               <Data ss:Type="String">GuidanceLineLightSystem - GuidanceLineLightSystem</Data>
            </Cell>
            <Cell>
               <Data ss:Type="String">=</Data>
            </Cell>
            <Cell>
               <Data ss:Type="String">1.0</Data>
            </Cell>
         </Row>
         <Row>
            <Cell>
               <Data ss:Type="String">CodeSurfacePreparationType - CodeSurfacePreparationType</Data>
            </Cell>
            <Cell>
               <Data ss:Type="String">=</Data>
            </Cell>
            <Cell>
               <Data ss:Type="String">1.0</Data>
            </Cell>
         </Row>
         <Row>
            <Cell>
               <Data ss:Type="String">TaxiHoldingPositionLightSystem - TaxiwayHoldingPositionLightSystem</Data>
            </Cell>
            <Cell>
               <Data ss:Type="String">=</Data>
            </Cell>
            <Cell>
               <Data ss:Type="String">1.0</Data>
            </Cell>
         </Row>
         <Row>
            <Cell>
               <Data ss:Type="String">CodeArrestingGearEnergyAbsorbType - CodeArrestingGearEnergyAbsorbType</Data>
            </Cell>
            <Cell>
               <Data ss:Type="String">=</Data>
            </Cell>
            <Cell>
               <Data ss:Type="String">1.0</Data>
            </Cell>
         </Row>
         <Row>
            <Cell>
               <Data ss:Type="String">RunwayDirectionLightSystem - RunwayDirectionLightSystem</Data>
            </Cell>
            <Cell>
               <Data ss:Type="String">=</Data>
            </Cell>
            <Cell>
               <Data ss:Type="String">1.0</Data>
            </Cell>
         </Row>
         <Row>
            <Cell>
               <Data ss:Type="String">CodePCNTyrePressureType - CodePCNTyrePressureType</Data>
            </Cell>
            <Cell>
               <Data ss:Type="String">=</Data>
            </Cell>
            <Cell>
               <Data ss:Type="String">1.0</Data>
            </Cell>
         </Row>
         <Row>
            <Cell>
               <Data ss:Type="String">CodePCNSubgradeType - CodePCNSubgradeType</Data>
            </Cell>
            <Cell>
               <Data ss:Type="String">=</Data>
            </Cell>
            <Cell>
               <Data ss:Type="String">1.0</Data>
            </Cell>
         </Row>
         <Row>
            <Cell>
               <Data ss:Type="String">TaxiwayContamination - AircraftStandContamination</Data>
            </Cell>
            <Cell>
               <Data ss:Type="String">=</Data>
            </Cell>
            <Cell>
               <Data ss:Type="String">0.9107096819832424</Data>
            </Cell>
         </Row>
         <Row>
            <Cell>
               <Data ss:Type="String">TaxiwayContamination - AerodromeContamination</Data>
            </Cell>
            <Cell>
               <Data ss:Type="String">=</Data>
            </Cell>
            <Cell>
               <Data ss:Type="String">0.9570748653553702</Data>
            </Cell>
         </Row>
         <Row>
            <Cell>
               <Data ss:Type="String">TaxiwayContamination - TaxiwayContamination</Data>
            </Cell>
            <Cell>
               <Data ss:Type="String">=</Data>
            </Cell>
            <Cell>
               <Data ss:Type="String">1.0</Data>
            </Cell>
         </Row>
         <Row>
            <Cell>
               <Data ss:Type="String">TaxiwayContamination - ApronContamination</Data>
            </Cell>
            <Cell>
               <Data ss:Type="String">=</Data>
            </Cell>
            <Cell>
               <Data ss:Type="String">0.9760824395456524</Data>
            </Cell>
         </Row>
         <Row>
            <Cell>
               <Data ss:Type="String">TaxiwayContamination - TouchDownLiftOffContamination</Data>
            </Cell>
            <Cell>
               <Data ss:Type="String">=</Data>
            </Cell>
            <Cell>
               <Data ss:Type="String">0.9418531931483778</Data>
            </Cell>
         </Row>
         <Row>
            <Cell>
               <Data ss:Type="String">TaxiwayContamination - RunwaySectionContamination</Data>
            </Cell>
            <Cell>
               <Data ss:Type="String">=</Data>
            </Cell>
            <Cell>
               <Data ss:Type="String">0.9682691108617034</Data>
            </Cell>
         </Row>
         <Row>
            <Cell>
               <Data ss:Type="String">TaxiwayContamination - RunwayContamination</Data>
            </Cell>
            <Cell>
               <Data ss:Type="String">=</Data>
            </Cell>
            <Cell>
               <Data ss:Type="String">0.9869215098532811</Data>
            </Cell>
         </Row>
         <Row>
            <Cell>
               <Data ss:Type="String">CodeApproachLightingType - CodeApproachLightingSystemType</Data>
            </Cell>
            <Cell>
               <Data ss:Type="String">=</Data>
            </Cell>
            <Cell>
               <Data ss:Type="String">1.0</Data>
            </Cell>
         </Row>
         <Row>
            <Cell>
               <Data ss:Type="String">TouchDownLiftOffContamination - TaxiwayContamination</Data>
            </Cell>
            <Cell>
               <Data ss:Type="String">=</Data>
            </Cell>
            <Cell>
               <Data ss:Type="String">0.9827340939315462</Data>
            </Cell>
         </Row>
         <Row>
            <Cell>
               <Data ss:Type="String">TouchDownLiftOffContamination - AerodromeContamination</Data>
            </Cell>
            <Cell>
               <Data ss:Type="String">=</Data>
            </Cell>
            <Cell>
               <Data ss:Type="String">0.9640710407941678</Data>
            </Cell>
         </Row>
         <Row>
            <Cell>
               <Data ss:Type="String">TouchDownLiftOffContamination - ApronContamination</Data>
            </Cell>
            <Cell>
               <Data ss:Type="String">=</Data>
            </Cell>
            <Cell>
               <Data ss:Type="String">0.982306426408287</Data>
            </Cell>
         </Row>
         <Row>
            <Cell>
               <Data ss:Type="String">TouchDownLiftOffContamination - AircraftStandContamination</Data>
            </Cell>
            <Cell>
               <Data ss:Type="String">=</Data>
            </Cell>
            <Cell>
               <Data ss:Type="String">0.9181458087775016</Data>
            </Cell>
         </Row>
         <Row>
            <Cell>
               <Data ss:Type="String">TouchDownLiftOffContamination - RunwaySectionContamination</Data>
            </Cell>
            <Cell>
               <Data ss:Type="String">=</Data>
            </Cell>
            <Cell>
               <Data ss:Type="String">0.9618148370398656</Data>
            </Cell>
         </Row>
         <Row>
            <Cell>
               <Data ss:Type="String">TouchDownLiftOffContamination - RunwayContamination</Data>
            </Cell>
            <Cell>
               <Data ss:Type="String">=</Data>
            </Cell>
            <Cell>
               <Data ss:Type="String">0.9802987977969034</Data>
            </Cell>
         </Row>
         <Row>
            <Cell>
               <Data ss:Type="String">TouchDownLiftOffContamination - TouchDownLiftOffContamination</Data>
            </Cell>
            <Cell>
               <Data ss:Type="String">=</Data>
            </Cell>
            <Cell>
               <Data ss:Type="String">0.965979381443299</Data>
            </Cell>
         </Row>
         <Row>
            <Cell>
               <Data ss:Type="String">CodeProtectAreaSectionType - CodeProtectAreaSectionType</Data>
            </Cell>
            <Cell>
               <Data ss:Type="String">=</Data>
            </Cell>
            <Cell>
               <Data ss:Type="String">1.0</Data>
            </Cell>
         </Row>
         <Row>
            <Cell>
               <Data ss:Type="String">CodeAirportWarningType - CodeAirportWarningType</Data>
            </Cell>
            <Cell>
               <Data ss:Type="String">=</Data>
            </Cell>
            <Cell>
               <Data ss:Type="String">1.0</Data>
            </Cell>
         </Row>
         <Row>
            <Cell>
               <Data ss:Type="String">CodeVASISType - CodeVASISType</Data>
            </Cell>
            <Cell>
               <Data ss:Type="String">=</Data>
            </Cell>
            <Cell>
               <Data ss:Type="String">1.0</Data>
            </Cell>
         </Row>
         <Row>
            <Cell>
               <Data ss:Type="String">CodeApronSectionType - CodeApronSectionType</Data>
            </Cell>
            <Cell>
               <Data ss:Type="String">=</Data>
            </Cell>
            <Cell>
               <Data ss:Type="String">1.0</Data>
            </Cell>
         </Row>
         <Row>
            <Cell>
               <Data ss:Type="String">TaxiHoldingPositionMarking - TaxiwayMarking</Data>
            </Cell>
            <Cell>
               <Data ss:Type="String">=</Data>
            </Cell>
            <Cell>
               <Data ss:Type="String">0.9167741935483871</Data>
            </Cell>
         </Row>
         <Row>
            <Cell>
               <Data ss:Type="String">TaxiHoldingPositionMarking - TaxiwayHoldingPositionMarking</Data>
            </Cell>
            <Cell>
               <Data ss:Type="String">=</Data>
            </Cell>
            <Cell>
               <Data ss:Type="String">0.9955223880597015</Data>
            </Cell>
         </Row>
         <Row>
            <Cell>
               <Data ss:Type="String">CodeTaxiwayElementType - CodeTaxiwayElementType</Data>
            </Cell>
            <Cell>
               <Data ss:Type="String">=</Data>
            </Cell>
            <Cell>
               <Data ss:Type="String">1.0</Data>
            </Cell>
         </Row>
         <Row>
            <Cell>
               <Data ss:Type="String">Apron - Apron</Data>
            </Cell>
            <Cell>
               <Data ss:Type="String">=</Data>
            </Cell>
            <Cell>
               <Data ss:Type="String">1.0</Data>
            </Cell>
         </Row>
         <Row>
            <Cell>
               <Data ss:Type="String">AirportProtectionAreaMarking - AerodromeProtectionAreaMarking</Data>
            </Cell>
            <Cell>
               <Data ss:Type="String">=</Data>
            </Cell>
            <Cell>
               <Data ss:Type="String">0.9734693877551021</Data>
            </Cell>
         </Row>
         <Row>
            <Cell>
               <Data ss:Type="String">CodeDeclaredDistanceType - CodeDeclaredDistanceType</Data>
            </Cell>
            <Cell>
               <Data ss:Type="String">=</Data>
            </Cell>
            <Cell>
               <Data ss:Type="String">1.0</Data>
            </Cell>
         </Row>
      </Table>
   </Worksheet>
</Workbook>