<?xml version="1.0" encoding="UTF-8"?>
<Workbook xmlns="urn:schemas-microsoft-com:office:spreadsheet" xmlns:x="urn:schemas-microsoft-com:office:excel" xmlns:ss="urn:schemas-microsoft-com:office:spreadsheet">
   <Worksheet ss:Name="Ark1">
      <Table x:FullColumns="1" x:FullRows="1">
         <Row>
            <Cell>
               <Data ss:Type="String">Correspondence</Data>
            </Cell>
            <Cell>
               <Data ss:Type="String">Relation</Data>
            </Cell>
            <Cell>
               <Data ss:Type="String">Measure</Data>
            </Cell>
         </Row>
         <Row>
            <Cell>
               <Data ss:Type="String">Marking - Marking</Data>
            </Cell>
            <Cell>
               <Data ss:Type="String">=</Data>
            </Cell>
            <Cell>
               <Data ss:Type="String">1.0</Data>
            </Cell>
         </Row>
         <Row>
            <Cell>
               <Data ss:Type="String">AirportHeliportUsage - AerodromeUsage</Data>
            </Cell>
            <Cell>
               <Data ss:Type="String">=</Data>
            </Cell>
            <Cell>
               <Data ss:Type="String">1.0</Data>
            </Cell>
         </Row>
         <Row>
            <Cell>
               <Data ss:Type="String">AirportHeliportUsage - ManoeuvringAreaUsage</Data>
            </Cell>
            <Cell>
               <Data ss:Type="String">=</Data>
            </Cell>
            <Cell>
               <Data ss:Type="String">1.0</Data>
            </Cell>
         </Row>
         <Row>
            <Cell>
               <Data ss:Type="String">NavaidEquipmentDistance - NavaidEquipmentDistance</Data>
            </Cell>
            <Cell>
               <Data ss:Type="String">=</Data>
            </Cell>
            <Cell>
               <Data ss:Type="String">1.0</Data>
            </Cell>
         </Row>
         <Row>
            <Cell>
               <Data ss:Type="String">NavaidEquipmentDistance - RunwayDeclaredDistance</Data>
            </Cell>
            <Cell>
               <Data ss:Type="String">=</Data>
            </Cell>
            <Cell>
               <Data ss:Type="String">0.5</Data>
            </Cell>
         </Row>
         <Row>
            <Cell>
               <Data ss:Type="String">ManoeuvringAreaAvailability - ManoeuvringAreaAvailability</Data>
            </Cell>
            <Cell>
               <Data ss:Type="String">=</Data>
            </Cell>
            <Cell>
               <Data ss:Type="String">1.0</Data>
            </Cell>
         </Row>
         <Row>
            <Cell>
               <Data ss:Type="String">ManoeuvringAreaAvailability - AerodromeAvailability</Data>
            </Cell>
            <Cell>
               <Data ss:Type="String">=</Data>
            </Cell>
            <Cell>
               <Data ss:Type="String">0.75</Data>
            </Cell>
         </Row>
         <Row>
            <Cell>
               <Data ss:Type="String">ManoeuvringAreaAvailability - ApronAreaAvailability</Data>
            </Cell>
            <Cell>
               <Data ss:Type="String">=</Data>
            </Cell>
            <Cell>
               <Data ss:Type="String">1.0</Data>
            </Cell>
         </Row>
         <Row>
            <Cell>
               <Data ss:Type="String">AirportHeliport - Aerodrome</Data>
            </Cell>
            <Cell>
               <Data ss:Type="String">=</Data>
            </Cell>
            <Cell>
               <Data ss:Type="String">0.5</Data>
            </Cell>
         </Row>
         <Row>
            <Cell>
               <Data ss:Type="String">GuidanceLineMarking - GuidanceLineMarking</Data>
            </Cell>
            <Cell>
               <Data ss:Type="String">=</Data>
            </Cell>
            <Cell>
               <Data ss:Type="String">1.0</Data>
            </Cell>
         </Row>
         <Row>
            <Cell>
               <Data ss:Type="String">ApronMarking - ApronMarking</Data>
            </Cell>
            <Cell>
               <Data ss:Type="String">=</Data>
            </Cell>
            <Cell>
               <Data ss:Type="String">1.0</Data>
            </Cell>
         </Row>
         <Row>
            <Cell>
               <Data ss:Type="String">GroundLightingAvailability - AerodromeSystem</Data>
            </Cell>
            <Cell>
               <Data ss:Type="String">=</Data>
            </Cell>
            <Cell>
               <Data ss:Type="String">0.5</Data>
            </Cell>
         </Row>
         <Row>
            <Cell>
               <Data ss:Type="String">GroundLightingAvailability - AltimeterSourceStatus</Data>
            </Cell>
            <Cell>
               <Data ss:Type="String">=</Data>
            </Cell>
            <Cell>
               <Data ss:Type="String">1.0</Data>
            </Cell>
         </Row>
         <Row>
            <Cell>
               <Data ss:Type="String">GroundLightingAvailability - GroundLightingAvailability</Data>
            </Cell>
            <Cell>
               <Data ss:Type="String">=</Data>
            </Cell>
            <Cell>
               <Data ss:Type="String">1.0</Data>
            </Cell>
         </Row>
         <Row>
            <Cell>
               <Data ss:Type="String">DeicingAreaMarking - DeicingAreaMarking</Data>
            </Cell>
            <Cell>
               <Data ss:Type="String">=</Data>
            </Cell>
            <Cell>
               <Data ss:Type="String">1.0</Data>
            </Cell>
         </Row>
         <Row>
            <Cell>
               <Data ss:Type="String">AltimeterSourceStatus - AltimeterSourceStatus</Data>
            </Cell>
            <Cell>
               <Data ss:Type="String">=</Data>
            </Cell>
            <Cell>
               <Data ss:Type="String">1.0</Data>
            </Cell>
         </Row>
         <Row>
            <Cell>
               <Data ss:Type="String">AltimeterSourceStatus - AerodromeSystem</Data>
            </Cell>
            <Cell>
               <Data ss:Type="String">=</Data>
            </Cell>
            <Cell>
               <Data ss:Type="String">0.5</Data>
            </Cell>
         </Row>
         <Row>
            <Cell>
               <Data ss:Type="String">AltimeterSourceStatus - GroundLightingAvailability</Data>
            </Cell>
            <Cell>
               <Data ss:Type="String">=</Data>
            </Cell>
            <Cell>
               <Data ss:Type="String">1.0</Data>
            </Cell>
         </Row>
         <Row>
            <Cell>
               <Data ss:Type="String">ManoeuvringAreaUsage - AerodromeUsage</Data>
            </Cell>
            <Cell>
               <Data ss:Type="String">=</Data>
            </Cell>
            <Cell>
               <Data ss:Type="String">0.5</Data>
            </Cell>
         </Row>
         <Row>
            <Cell>
               <Data ss:Type="String">ManoeuvringAreaUsage - ManoeuvringAreaUsage</Data>
            </Cell>
            <Cell>
               <Data ss:Type="String">=</Data>
            </Cell>
            <Cell>
               <Data ss:Type="String">0.5</Data>
            </Cell>
         </Row>
         <Row>
            <Cell>
               <Data ss:Type="String">ApronElement - ApronElement</Data>
            </Cell>
            <Cell>
               <Data ss:Type="String">=</Data>
            </Cell>
            <Cell>
               <Data ss:Type="String">0.6</Data>
            </Cell>
         </Row>
         <Row>
            <Cell>
               <Data ss:Type="String">ApronElement - TaxiwayElement</Data>
            </Cell>
            <Cell>
               <Data ss:Type="String">=</Data>
            </Cell>
            <Cell>
               <Data ss:Type="String">0.5</Data>
            </Cell>
         </Row>
         <Row>
            <Cell>
               <Data ss:Type="String">DeicingArea - DeicingArea</Data>
            </Cell>
            <Cell>
               <Data ss:Type="String">=</Data>
            </Cell>
            <Cell>
               <Data ss:Type="String">0.5</Data>
            </Cell>
         </Row>
         <Row>
            <Cell>
               <Data ss:Type="String">TaxiwayMarking - TaxiwayMarking</Data>
            </Cell>
            <Cell>
               <Data ss:Type="String">=</Data>
            </Cell>
            <Cell>
               <Data ss:Type="String">1.0</Data>
            </Cell>
         </Row>
         <Row>
            <Cell>
               <Data ss:Type="String">ApproachLightingSystem - ApproachLightingSystem</Data>
            </Cell>
            <Cell>
               <Data ss:Type="String">=</Data>
            </Cell>
            <Cell>
               <Data ss:Type="String">1.0</Data>
            </Cell>
         </Row>
         <Row>
            <Cell>
               <Data ss:Type="String">AirportHeliportResponsibilityOrganisation - AerodromeResponsibilityOrganisation</Data>
            </Cell>
            <Cell>
               <Data ss:Type="String">=</Data>
            </Cell>
            <Cell>
               <Data ss:Type="String">1.0</Data>
            </Cell>
         </Row>
         <Row>
            <Cell>
               <Data ss:Type="String">RunwayDeclaredDistanceValue - NavaidEquipmentDistance</Data>
            </Cell>
            <Cell>
               <Data ss:Type="String">=</Data>
            </Cell>
            <Cell>
               <Data ss:Type="String">1.0</Data>
            </Cell>
         </Row>
         <Row>
            <Cell>
               <Data ss:Type="String">RunwayDeclaredDistanceValue - RunwayDeclaredDistance</Data>
            </Cell>
            <Cell>
               <Data ss:Type="String">=</Data>
            </Cell>
            <Cell>
               <Data ss:Type="String">0.5</Data>
            </Cell>
         </Row>
         <Row>
            <Cell>
               <Data ss:Type="String">RunwayProtectAreaLightSystem - ApronLightSystem</Data>
            </Cell>
            <Cell>
               <Data ss:Type="String">=</Data>
            </Cell>
            <Cell>
               <Data ss:Type="String">0.5</Data>
            </Cell>
         </Row>
         <Row>
            <Cell>
               <Data ss:Type="String">RunwayProtectAreaLightSystem - TaxiwayLightSystem</Data>
            </Cell>
            <Cell>
               <Data ss:Type="String">=</Data>
            </Cell>
            <Cell>
               <Data ss:Type="String">0.5</Data>
            </Cell>
         </Row>
         <Row>
            <Cell>
               <Data ss:Type="String">RunwayProtectAreaLightSystem - RunwayProtectAreaLightSystem</Data>
            </Cell>
            <Cell>
               <Data ss:Type="String">=</Data>
            </Cell>
            <Cell>
               <Data ss:Type="String">1.0</Data>
            </Cell>
         </Row>
         <Row>
            <Cell>
               <Data ss:Type="String">RunwayProtectAreaLightSystem - TouchDownLiftOffLightSystem</Data>
            </Cell>
            <Cell>
               <Data ss:Type="String">=</Data>
            </Cell>
            <Cell>
               <Data ss:Type="String">0.5</Data>
            </Cell>
         </Row>
         <Row>
            <Cell>
               <Data ss:Type="String">RunwayProtectArea - RunwayProtectArea</Data>
            </Cell>
            <Cell>
               <Data ss:Type="String">=</Data>
            </Cell>
            <Cell>
               <Data ss:Type="String">0.6666666666666666</Data>
            </Cell>
         </Row>
         <Row>
            <Cell>
               <Data ss:Type="String">RunwayProtectArea - PassengerLoadingBridge</Data>
            </Cell>
            <Cell>
               <Data ss:Type="String">=</Data>
            </Cell>
            <Cell>
               <Data ss:Type="String">0.5</Data>
            </Cell>
         </Row>
         <Row>
            <Cell>
               <Data ss:Type="String">RunwayDeclaredDistance - PassengerLoadingBridge</Data>
            </Cell>
            <Cell>
               <Data ss:Type="String">=</Data>
            </Cell>
            <Cell>
               <Data ss:Type="String">0.5</Data>
            </Cell>
         </Row>
         <Row>
            <Cell>
               <Data ss:Type="String">ArrestingGear - ArrestingGear</Data>
            </Cell>
            <Cell>
               <Data ss:Type="String">=</Data>
            </Cell>
            <Cell>
               <Data ss:Type="String">0.5</Data>
            </Cell>
         </Row>
         <Row>
            <Cell>
               <Data ss:Type="String">TaxiwayElement - TaxiwayElement</Data>
            </Cell>
            <Cell>
               <Data ss:Type="String">=</Data>
            </Cell>
            <Cell>
               <Data ss:Type="String">0.6666666666666666</Data>
            </Cell>
         </Row>
         <Row>
            <Cell>
               <Data ss:Type="String">TaxiwayElement - RunwayElement</Data>
            </Cell>
            <Cell>
               <Data ss:Type="String">=</Data>
            </Cell>
            <Cell>
               <Data ss:Type="String">0.5454545454545454</Data>
            </Cell>
         </Row>
         <Row>
            <Cell>
               <Data ss:Type="String">RunwayBlastPad - RunwayBlastPad</Data>
            </Cell>
            <Cell>
               <Data ss:Type="String">=</Data>
            </Cell>
            <Cell>
               <Data ss:Type="String">0.5714285714285714</Data>
            </Cell>
         </Row>
         <Row>
            <Cell>
               <Data ss:Type="String">TouchDownLiftOff - TouchDownLiftOff</Data>
            </Cell>
            <Cell>
               <Data ss:Type="String">=</Data>
            </Cell>
            <Cell>
               <Data ss:Type="String">0.625</Data>
            </Cell>
         </Row>
         <Row>
            <Cell>
               <Data ss:Type="String">PassengerLoadingBridge - PassengerLoadingBridge</Data>
            </Cell>
            <Cell>
               <Data ss:Type="String">=</Data>
            </Cell>
            <Cell>
               <Data ss:Type="String">0.5</Data>
            </Cell>
         </Row>
         <Row>
            <Cell>
               <Data ss:Type="String">TouchDownLiftOffMarking - TouchDownLiftOffMarking</Data>
            </Cell>
            <Cell>
               <Data ss:Type="String">=</Data>
            </Cell>
            <Cell>
               <Data ss:Type="String">1.0</Data>
            </Cell>
         </Row>
         <Row>
            <Cell>
               <Data ss:Type="String">ApronLightSystem - ApronLightSystem</Data>
            </Cell>
            <Cell>
               <Data ss:Type="String">=</Data>
            </Cell>
            <Cell>
               <Data ss:Type="String">0.5</Data>
            </Cell>
         </Row>
         <Row>
            <Cell>
               <Data ss:Type="String">ApronLightSystem - TaxiwayLightSystem</Data>
            </Cell>
            <Cell>
               <Data ss:Type="String">=</Data>
            </Cell>
            <Cell>
               <Data ss:Type="String">0.5</Data>
            </Cell>
         </Row>
         <Row>
            <Cell>
               <Data ss:Type="String">ApronLightSystem - TouchDownLiftOffLightSystem</Data>
            </Cell>
            <Cell>
               <Data ss:Type="String">=</Data>
            </Cell>
            <Cell>
               <Data ss:Type="String">0.5</Data>
            </Cell>
         </Row>
         <Row>
            <Cell>
               <Data ss:Type="String">StandMarking - StandMarking</Data>
            </Cell>
            <Cell>
               <Data ss:Type="String">=</Data>
            </Cell>
            <Cell>
               <Data ss:Type="String">1.0</Data>
            </Cell>
         </Row>
         <Row>
            <Cell>
               <Data ss:Type="String">MarkingElement - MarkingElement</Data>
            </Cell>
            <Cell>
               <Data ss:Type="String">=</Data>
            </Cell>
            <Cell>
               <Data ss:Type="String">0.6666666666666666</Data>
            </Cell>
         </Row>
         <Row>
            <Cell>
               <Data ss:Type="String">AircraftStand - AircraftStand</Data>
            </Cell>
            <Cell>
               <Data ss:Type="String">=</Data>
            </Cell>
            <Cell>
               <Data ss:Type="String">0.5454545454545454</Data>
            </Cell>
         </Row>
         <Row>
            <Cell>
               <Data ss:Type="String">Runway - Runway</Data>
            </Cell>
            <Cell>
               <Data ss:Type="String">=</Data>
            </Cell>
            <Cell>
               <Data ss:Type="String">0.875</Data>
            </Cell>
         </Row>
         <Row>
            <Cell>
               <Data ss:Type="String">Road - Road</Data>
            </Cell>
            <Cell>
               <Data ss:Type="String">=</Data>
            </Cell>
            <Cell>
               <Data ss:Type="String">0.625</Data>
            </Cell>
         </Row>
         <Row>
            <Cell>
               <Data ss:Type="String">Taxiway - Taxiway</Data>
            </Cell>
            <Cell>
               <Data ss:Type="String">=</Data>
            </Cell>
            <Cell>
               <Data ss:Type="String">0.7272727272727273</Data>
            </Cell>
         </Row>
         <Row>
            <Cell>
               <Data ss:Type="String">MarkingBuoy - MarkingBuoy</Data>
            </Cell>
            <Cell>
               <Data ss:Type="String">=</Data>
            </Cell>
            <Cell>
               <Data ss:Type="String">0.8</Data>
            </Cell>
         </Row>
         <Row>
            <Cell>
               <Data ss:Type="String">TaxiwayLightSystem - ApronLightSystem</Data>
            </Cell>
            <Cell>
               <Data ss:Type="String">=</Data>
            </Cell>
            <Cell>
               <Data ss:Type="String">0.5</Data>
            </Cell>
         </Row>
         <Row>
            <Cell>
               <Data ss:Type="String">TaxiwayLightSystem - TaxiwayLightSystem</Data>
            </Cell>
            <Cell>
               <Data ss:Type="String">=</Data>
            </Cell>
            <Cell>
               <Data ss:Type="String">0.5</Data>
            </Cell>
         </Row>
         <Row>
            <Cell>
               <Data ss:Type="String">TaxiwayLightSystem - TouchDownLiftOffLightSystem</Data>
            </Cell>
            <Cell>
               <Data ss:Type="String">=</Data>
            </Cell>
            <Cell>
               <Data ss:Type="String">0.5</Data>
            </Cell>
         </Row>
         <Row>
            <Cell>
               <Data ss:Type="String">TouchDownLiftOffLightSystem - TouchDownLiftOffLightSystem</Data>
            </Cell>
            <Cell>
               <Data ss:Type="String">=</Data>
            </Cell>
            <Cell>
               <Data ss:Type="String">0.5</Data>
            </Cell>
         </Row>
         <Row>
            <Cell>
               <Data ss:Type="String">TouchDownLiftOffLightSystem - ApronLightSystem</Data>
            </Cell>
            <Cell>
               <Data ss:Type="String">=</Data>
            </Cell>
            <Cell>
               <Data ss:Type="String">0.5</Data>
            </Cell>
         </Row>
         <Row>
            <Cell>
               <Data ss:Type="String">TouchDownLiftOffLightSystem - TaxiwayLightSystem</Data>
            </Cell>
            <Cell>
               <Data ss:Type="String">=</Data>
            </Cell>
            <Cell>
               <Data ss:Type="String">0.5</Data>
            </Cell>
         </Row>
         <Row>
            <Cell>
               <Data ss:Type="String">TouchDownLiftOffSafeArea - TouchDownLiftOffSafeArea</Data>
            </Cell>
            <Cell>
               <Data ss:Type="String">=</Data>
            </Cell>
            <Cell>
               <Data ss:Type="String">1.0</Data>
            </Cell>
         </Row>
         <Row>
            <Cell>
               <Data ss:Type="String">AirportHeliportProtectionArea - AerodromeProtectionArea</Data>
            </Cell>
            <Cell>
               <Data ss:Type="String">=</Data>
            </Cell>
            <Cell>
               <Data ss:Type="String">0.75</Data>
            </Cell>
         </Row>
         <Row>
            <Cell>
               <Data ss:Type="String">VisualGlideSlopeIndicator - VisualGlideSlopeIndicator</Data>
            </Cell>
            <Cell>
               <Data ss:Type="String">=</Data>
            </Cell>
            <Cell>
               <Data ss:Type="String">0.7142857142857143</Data>
            </Cell>
         </Row>
         <Row>
            <Cell>
               <Data ss:Type="String">GroundLightSystem - GroundLightSystem</Data>
            </Cell>
            <Cell>
               <Data ss:Type="String">=</Data>
            </Cell>
            <Cell>
               <Data ss:Type="String">1.0</Data>
            </Cell>
         </Row>
         <Row>
            <Cell>
               <Data ss:Type="String">SeaplaneLandingArea - SeaplaneLandingArea</Data>
            </Cell>
            <Cell>
               <Data ss:Type="String">=</Data>
            </Cell>
            <Cell>
               <Data ss:Type="String">0.75</Data>
            </Cell>
         </Row>
         <Row>
            <Cell>
               <Data ss:Type="String">GuidanceLineLightSystem - GuidanceLineLightSystem</Data>
            </Cell>
            <Cell>
               <Data ss:Type="String">=</Data>
            </Cell>
            <Cell>
               <Data ss:Type="String">1.0</Data>
            </Cell>
         </Row>
         <Row>
            <Cell>
               <Data ss:Type="String">WorkArea - WorkArea</Data>
            </Cell>
            <Cell>
               <Data ss:Type="String">=</Data>
            </Cell>
            <Cell>
               <Data ss:Type="String">0.5</Data>
            </Cell>
         </Row>
         <Row>
            <Cell>
               <Data ss:Type="String">RunwayElement - TaxiwayElement</Data>
            </Cell>
            <Cell>
               <Data ss:Type="String">=</Data>
            </Cell>
            <Cell>
               <Data ss:Type="String">0.6</Data>
            </Cell>
         </Row>
         <Row>
            <Cell>
               <Data ss:Type="String">RunwayElement - RunwayElement</Data>
            </Cell>
            <Cell>
               <Data ss:Type="String">=</Data>
            </Cell>
            <Cell>
               <Data ss:Type="String">0.6363636363636364</Data>
            </Cell>
         </Row>
         <Row>
            <Cell>
               <Data ss:Type="String">TaxiHoldingPositionLightSystem - PassengerLoadingBridge</Data>
            </Cell>
            <Cell>
               <Data ss:Type="String">=</Data>
            </Cell>
            <Cell>
               <Data ss:Type="String">0.5</Data>
            </Cell>
         </Row>
         <Row>
            <Cell>
               <Data ss:Type="String">AltimeterSource - AltimeterSource</Data>
            </Cell>
            <Cell>
               <Data ss:Type="String">=</Data>
            </Cell>
            <Cell>
               <Data ss:Type="String">1.0</Data>
            </Cell>
         </Row>
         <Row>
            <Cell>
               <Data ss:Type="String">RunwayDirectionLightSystem - TouchDownLiftOffLightSystem</Data>
            </Cell>
            <Cell>
               <Data ss:Type="String">=</Data>
            </Cell>
            <Cell>
               <Data ss:Type="String">0.5</Data>
            </Cell>
         </Row>
         <Row>
            <Cell>
               <Data ss:Type="String">RunwayDirectionLightSystem - TaxiwayLightSystem</Data>
            </Cell>
            <Cell>
               <Data ss:Type="String">=</Data>
            </Cell>
            <Cell>
               <Data ss:Type="String">0.5</Data>
            </Cell>
         </Row>
         <Row>
            <Cell>
               <Data ss:Type="String">RunwayDirectionLightSystem - ApronLightSystem</Data>
            </Cell>
            <Cell>
               <Data ss:Type="String">=</Data>
            </Cell>
            <Cell>
               <Data ss:Type="String">0.5</Data>
            </Cell>
         </Row>
         <Row>
            <Cell>
               <Data ss:Type="String">RunwayDirectionLightSystem - RunwayDirectionLightSystem</Data>
            </Cell>
            <Cell>
               <Data ss:Type="String">=</Data>
            </Cell>
            <Cell>
               <Data ss:Type="String">1.0</Data>
            </Cell>
         </Row>
         <Row>
            <Cell>
               <Data ss:Type="String">AirportHeliportAvailability - ApronAreaAvailability</Data>
            </Cell>
            <Cell>
               <Data ss:Type="String">=</Data>
            </Cell>
            <Cell>
               <Data ss:Type="String">1.0</Data>
            </Cell>
         </Row>
         <Row>
            <Cell>
               <Data ss:Type="String">AirportHeliportAvailability - ManoeuvringAreaAvailability</Data>
            </Cell>
            <Cell>
               <Data ss:Type="String">=</Data>
            </Cell>
            <Cell>
               <Data ss:Type="String">1.0</Data>
            </Cell>
         </Row>
         <Row>
            <Cell>
               <Data ss:Type="String">AirportHeliportAvailability - AerodromeAvailability</Data>
            </Cell>
            <Cell>
               <Data ss:Type="String">=</Data>
            </Cell>
            <Cell>
               <Data ss:Type="String">0.75</Data>
            </Cell>
         </Row>
         <Row>
            <Cell>
               <Data ss:Type="String">ApronAreaAvailability - AerodromeAvailability</Data>
            </Cell>
            <Cell>
               <Data ss:Type="String">=</Data>
            </Cell>
            <Cell>
               <Data ss:Type="String">0.75</Data>
            </Cell>
         </Row>
         <Row>
            <Cell>
               <Data ss:Type="String">ApronAreaAvailability - ManoeuvringAreaAvailability</Data>
            </Cell>
            <Cell>
               <Data ss:Type="String">=</Data>
            </Cell>
            <Cell>
               <Data ss:Type="String">1.0</Data>
            </Cell>
         </Row>
         <Row>
            <Cell>
               <Data ss:Type="String">ApronAreaAvailability - ApronAreaAvailability</Data>
            </Cell>
            <Cell>
               <Data ss:Type="String">=</Data>
            </Cell>
            <Cell>
               <Data ss:Type="String">1.0</Data>
            </Cell>
         </Row>
         <Row>
            <Cell>
               <Data ss:Type="String">SurfaceCharacteristics - SurfaceCharacteristics</Data>
            </Cell>
            <Cell>
               <Data ss:Type="String">=</Data>
            </Cell>
            <Cell>
               <Data ss:Type="String">1.0</Data>
            </Cell>
         </Row>
         <Row>
            <Cell>
               <Data ss:Type="String">Apron - Apron</Data>
            </Cell>
            <Cell>
               <Data ss:Type="String">=</Data>
            </Cell>
            <Cell>
               <Data ss:Type="String">0.5</Data>
            </Cell>
         </Row>
         <Row>
            <Cell>
               <Data ss:Type="String">AirportProtectionAreaMarking - AerodromeProtectionAreaMarking</Data>
            </Cell>
            <Cell>
               <Data ss:Type="String">=</Data>
            </Cell>
            <Cell>
               <Data ss:Type="String">1.0</Data>
            </Cell>
         </Row>
      </Table>
   </Worksheet>
</Workbook>