<?xml version="1.0" encoding="UTF-8" standalone="no"?>
<catalog prefer="public" xmlns="urn:oasis:names:tc:entity:xmlns:xml:catalog">
    <group id="Folder Repository, directory=, recursive=true, Auto-Update=true, version=2" prefer="public" xml:base="">
        <uri id="Automatically generated entry, Timestamp=1550131619357" name="ontolearning.owl" uri="UoA/ontolearning.owl"/>
        <uri id="Automatically generated entry, Timestamp=1550131619357" name="http://cmt" uri="OAEI-16-conference/ontologies/cmt.owl"/>
        <uri id="Automatically generated entry, Timestamp=1550131619357" name="http://conference" uri="ontologies/Conference.owl"/>
        <uri id="Automatically generated entry, Timestamp=1550131619357" name="http://confOf" uri="OAEI-16-conference/ontologies/confOf.owl"/>
        <uri id="Automatically generated entry, Timestamp=1550131619357" name="http://data.doremus.org/ontology#" uri="ntnu-lyon-paper/ontologies/doremus.owl"/>
        <uri id="Automatically generated entry, Timestamp=1550131619357" name="http://dbpedia.org/ontology/" uri="wndomainsexperiment/dbpedia_2014.owl"/>
        <uri id="Automatically generated entry, Timestamp=1550131619357" name="http://dbpedia.org/ontology/sample/" uri="UoA/dbpedia.owl"/>
        <uri id="Automatically generated entry, Timestamp=1550131619357" name="http://denia.idi.ntnu.no/TestTransportWithInstances1.owl" uri="UoA/TestTransportWithInstances1.owl"/>
        <uri id="Automatically generated entry, Timestamp=1550131619357" name="http://denia.idi.ntnu.no/TestTransportWithInstances2" uri="UoA/TestTransportWithInstances2.owl"/>
        <uri id="Automatically generated entry, Timestamp=1550131619357" name="http://denia.idi.ntnu.no/phd/transportmeans.owl" uri="_PHD_EVALUATION/MATCHERTESTING/transportmeans.owl"/>
        <uri id="Automatically generated entry, Timestamp=1550131619357" name="http://ebiquity.umbc.edu/v2.1/ontology/publication.owl" uri="ER2017/302303/302.rdf"/>
        <uri id="Automatically generated entry, Timestamp=1550131619357" name="http://ebiquity.umbc.edu/v2.1/ontology/publication.owl#" uri="OAEI2009/302/onto.rdf"/>
        <uri id="Automatically generated entry, Timestamp=1550131619357" name="http://edas" uri="OAEI-16-conference/ontologies/edas.owl"/>
        <uri id="Automatically generated entry, Timestamp=1550131619357" name="http://ekaw" uri="ontologies/ekaw.owl"/>
        <uri id="Automatically generated entry, Timestamp=1550131619357" name="http://iasted" uri="OAEI-16-conference/ontologies/iasted.owl"/>
        <uri id="Automatically generated entry, Timestamp=1550131619357" name="http://id.loc.gov/ontologies/bibframe" uri="bibframe.rdf"/>
        <uri id="Automatically generated entry, Timestamp=1550131619357" name="http://id.loc.gov/ontologies/bibframe/" uri="ESWC_ATMONTO_AIRM/bibframe.rdf"/>
        <uri id="Automatically generated entry, Timestamp=1550131619357" name="http://knowledgeweb.semanticweb.org/heterogeneity/alignment#" uri="omwg/travel.xml"/>
        <uri id="Automatically generated entry, Timestamp=1550131619357" name="http://musicbrainz.org/mm/mm-2.1" uri="ntnu-lyon-paper/ontologies/MusicBrainz.owl"/>
        <uri id="Automatically generated entry, Timestamp=1550131619357" name="http://ns.inria.org/edoal/1.0/#" uri="omwg/transf.rdf"/>
        <uri id="Automatically generated entry, Timestamp=1550131619357" name="http://oaei.ontologymatching.org/2006/benchmarks/101/onto.rdf" uri="OAEI2009/101/101.rdf"/>
        <uri id="Automatically generated entry, Timestamp=1550131619357" name="http://oaei.ontologymatching.org/2006/benchmarks/103/onto.rdf#" uri="OAEI2009/103/onto.rdf"/>
        <uri id="Automatically generated entry, Timestamp=1550131619357" name="http://oaei.ontologymatching.org/2006/benchmarks/104/onto.rdf#" uri="OAEI2009/104/onto.rdf"/>
        <uri id="Automatically generated entry, Timestamp=1550131619357" name="http://oaei.ontologymatching.org/2006/benchmarks/201/onto.rdf#" uri="OAEI2009/201/onto.rdf"/>
        <uri id="Automatically generated entry, Timestamp=1550131619357" name="http://oaei.ontologymatching.org/2006/benchmarks/202/onto.rdf#" uri="OAEI2009/202/onto.rdf"/>
        <uri id="Automatically generated entry, Timestamp=1550131619357" name="http://oaei.ontologymatching.org/2006/benchmarks/203/onto.rdf#" uri="OAEI2009/203/onto.rdf"/>
        <uri id="Automatically generated entry, Timestamp=1550131619357" name="http://oaei.ontologymatching.org/2006/benchmarks/204/onto.rdf#" uri="OAEI2009/204/onto.rdf"/>
        <uri id="Automatically generated entry, Timestamp=1550131619357" name="http://oaei.ontologymatching.org/2006/benchmarks/205/onto.rdf#" uri="OAEI2009/205/onto.rdf"/>
        <uri id="Automatically generated entry, Timestamp=1550131619357" name="duplicate:http://oaei.ontologymatching.org/2006/benchmarks/206/onto.rdf#" uri="OAEI2009/206/onto.rdf"/>
        <uri id="Automatically generated entry, Timestamp=1550131619357" name="duplicate:http://oaei.ontologymatching.org/2006/benchmarks/206/onto.rdf#" uri="OAEI2009/206/onto-iso8859.rdf"/>
        <uri id="Automatically generated entry, Timestamp=1550131619357" name="duplicate:http://oaei.ontologymatching.org/2006/benchmarks/207/onto.rdf#" uri="OAEI2009/207/onto.rdf"/>
        <uri id="Automatically generated entry, Timestamp=1550131619357" name="duplicate:http://oaei.ontologymatching.org/2006/benchmarks/207/onto.rdf#" uri="OAEI2009/207/onto-iso8859.rdf"/>
        <uri id="Automatically generated entry, Timestamp=1550131619357" name="http://oaei.ontologymatching.org/2006/benchmarks/208/onto.rdf#" uri="OAEI2009/208/onto.rdf"/>
        <uri id="Automatically generated entry, Timestamp=1550131619357" name="http://oaei.ontologymatching.org/2006/benchmarks/209/onto.rdf#" uri="OAEI2009/209/onto.rdf"/>
        <uri id="Automatically generated entry, Timestamp=1550131619357" name="duplicate:http://oaei.ontologymatching.org/2006/benchmarks/210/onto.rdf#" uri="OAEI2009/210/onto.rdf"/>
        <uri id="Automatically generated entry, Timestamp=1550131619357" name="duplicate:http://oaei.ontologymatching.org/2006/benchmarks/210/onto.rdf#" uri="OAEI2009/210/onto-iso8859.rdf"/>
        <uri id="Automatically generated entry, Timestamp=1550131619357" name="http://oaei.ontologymatching.org/2006/benchmarks/222/onto.rdf#" uri="OAEI2009/222/onto.rdf"/>
        <uri id="Automatically generated entry, Timestamp=1550131619357" name="http://oaei.ontologymatching.org/2006/benchmarks/223/onto.rdf#" uri="OAEI2009/223/onto.rdf"/>
        <uri id="Automatically generated entry, Timestamp=1550131619357" name="http://oaei.ontologymatching.org/2006/benchmarks/224/onto.rdf#" uri="OAEI2009/224/onto.rdf"/>
        <uri id="Automatically generated entry, Timestamp=1550131619357" name="http://oaei.ontologymatching.org/2006/benchmarks/225/onto.rdf#" uri="OAEI2009/225/onto.rdf"/>
        <uri id="Automatically generated entry, Timestamp=1550131619357" name="http://oaei.ontologymatching.org/2006/benchmarks/230/onto.rdf#" uri="OAEI2009/230/onto.rdf"/>
        <uri id="Automatically generated entry, Timestamp=1550131619357" name="http://oaei.ontologymatching.org/2006/benchmarks/231/onto.rdf#" uri="OAEI2009/231/onto.rdf"/>
        <uri id="Automatically generated entry, Timestamp=1550131619357" name="http://oaei.ontologymatching.org/2006/benchmarks/237/onto.rdf#" uri="OAEI2009/237/onto.rdf"/>
        <uri id="Automatically generated entry, Timestamp=1550131619357" name="http://oaei.ontologymatching.org/2006/benchmarks/238/onto.rdf#" uri="OAEI2009/238/onto.rdf"/>
        <uri id="Automatically generated entry, Timestamp=1550131619357" name="http://oaei.ontologymatching.org/2006/benchmarks/249/onto.rdf#" uri="OAEI2009/249/onto.rdf"/>
        <uri id="Automatically generated entry, Timestamp=1550131619357" name="http://oaei.ontologymatching.org/2006/benchmarks/251/onto.rdf#" uri="OAEI2009/251/onto.rdf"/>
        <uri id="Automatically generated entry, Timestamp=1550131619357" name="http://oaei.ontologymatching.org/2006/benchmarks/252/onto.rdf#" uri="OAEI2009/252/onto.rdf"/>
        <uri id="Automatically generated entry, Timestamp=1550131619357" name="http://oaei.ontologymatching.org/2006/benchmarks/258/onto.rdf#" uri="OAEI2009/258/onto.rdf"/>
        <uri id="Automatically generated entry, Timestamp=1550131619357" name="http://oaei.ontologymatching.org/2006/benchmarks/259/onto.rdf#" uri="OAEI2009/259/onto.rdf"/>
        <uri id="Automatically generated entry, Timestamp=1550131619357" name="http://oaei.ontologymatching.org/2006/benchmarks/301/onto.rdf#" uri="OAEI2009/301/onto.rdf"/>
        <uri id="Automatically generated entry, Timestamp=1550131619357" name="http://oaei.ontologymatching.org/2006/benchmarks/304/onto.rdf#" uri="OAEI2009/304/onto.rdf"/>
        <uri id="Automatically generated entry, Timestamp=1550131619357" name="http://oaei.ontologymatching.org/2009/benchmarks/304/onto.rdf" uri="ER2017/303304/304.rdf"/>
        <uri id="Automatically generated entry, Timestamp=1550131619357" name="http://oaei.ontologymatching.org/2010/benchmarks/301/onto.rdf" uri="ER2017/301303/301.rdf"/>
        <uri id="Automatically generated entry, Timestamp=1550131619357" name="http://oaei.ontologymatching.org/2016benchmarks/biblio/1//101/onto.rdf#" uri="OAEI2016Benchmark/101/onto.rdf"/>
        <uri id="Automatically generated entry, Timestamp=1550131619357" name="http://oaei.ontologymatching.org/2016benchmarks/biblio/1//201-2/onto.rdf#" uri="OAEI2016Benchmark/201-2/onto.rdf"/>
        <uri id="Automatically generated entry, Timestamp=1550131619357" name="http://oaei.ontologymatching.org/2016benchmarks/biblio/1//201-4/onto.rdf#" uri="OAEI2016Benchmark/201-4/onto.rdf"/>
        <uri id="Automatically generated entry, Timestamp=1550131619357" name="http://oaei.ontologymatching.org/2016benchmarks/biblio/1//201-6/onto.rdf#" uri="OAEI2016Benchmark/201-6/onto.rdf"/>
        <uri id="Automatically generated entry, Timestamp=1550131619357" name="http://oaei.ontologymatching.org/2016benchmarks/biblio/1//201-8/onto.rdf#" uri="OAEI2016Benchmark/201-8/onto.rdf"/>
        <uri id="Automatically generated entry, Timestamp=1550131619357" name="http://oaei.ontologymatching.org/2016benchmarks/biblio/1//201/onto.rdf#" uri="OAEI2016Benchmark/201/onto.rdf"/>
        <uri id="Automatically generated entry, Timestamp=1550131619357" name="http://oaei.ontologymatching.org/2016benchmarks/biblio/1//202-2/onto.rdf#" uri="OAEI2016Benchmark/202-2/onto.rdf"/>
        <uri id="Automatically generated entry, Timestamp=1550131619357" name="http://oaei.ontologymatching.org/2016benchmarks/biblio/1//202-4/onto.rdf#" uri="OAEI2016Benchmark/202-4/onto.rdf"/>
        <uri id="Automatically generated entry, Timestamp=1550131619357" name="http://oaei.ontologymatching.org/2016benchmarks/biblio/1//202-6/onto.rdf#" uri="OAEI2016Benchmark/202-6/onto.rdf"/>
        <uri id="Automatically generated entry, Timestamp=1550131619357" name="http://oaei.ontologymatching.org/2016benchmarks/biblio/1//202-8/onto.rdf#" uri="OAEI2016Benchmark/202-8/onto.rdf"/>
        <uri id="Automatically generated entry, Timestamp=1550131619357" name="http://oaei.ontologymatching.org/2016benchmarks/biblio/1//202/onto.rdf#" uri="OAEI2016Benchmark/202/onto.rdf"/>
        <uri id="Automatically generated entry, Timestamp=1550131619357" name="http://oaei.ontologymatching.org/2016benchmarks/biblio/1//221/onto.rdf#" uri="OAEI2016Benchmark/221/onto.rdf"/>
        <uri id="Automatically generated entry, Timestamp=1550131619357" name="http://oaei.ontologymatching.org/2016benchmarks/biblio/1//222/onto.rdf#" uri="OAEI2016Benchmark/222/onto.rdf"/>
        <uri id="Automatically generated entry, Timestamp=1550131619357" name="http://oaei.ontologymatching.org/2016benchmarks/biblio/1//223/onto.rdf#" uri="OAEI2016Benchmark/223/onto.rdf"/>
        <uri id="Automatically generated entry, Timestamp=1550131619357" name="http://oaei.ontologymatching.org/2016benchmarks/biblio/1//224/onto.rdf#" uri="OAEI2016Benchmark/224/onto.rdf"/>
        <uri id="Automatically generated entry, Timestamp=1550131619357" name="http://oaei.ontologymatching.org/2016benchmarks/biblio/1//225/onto.rdf#" uri="OAEI2016Benchmark/225/onto.rdf"/>
        <uri id="Automatically generated entry, Timestamp=1550131619357" name="http://oaei.ontologymatching.org/2016benchmarks/biblio/1//228/onto.rdf#" uri="OAEI2016Benchmark/228/onto.rdf"/>
        <uri id="Automatically generated entry, Timestamp=1550131619357" name="http://oaei.ontologymatching.org/2016benchmarks/biblio/1//232/onto.rdf#" uri="OAEI2016Benchmark/232/onto.rdf"/>
        <uri id="Automatically generated entry, Timestamp=1550131619357" name="http://oaei.ontologymatching.org/2016benchmarks/biblio/1//233/onto.rdf#" uri="OAEI2016Benchmark/233/onto.rdf"/>
        <uri id="Automatically generated entry, Timestamp=1550131619357" name="http://oaei.ontologymatching.org/2016benchmarks/biblio/1//236/onto.rdf#" uri="OAEI2016Benchmark/236/onto.rdf"/>
        <uri id="Automatically generated entry, Timestamp=1550131619357" name="http://oaei.ontologymatching.org/2016benchmarks/biblio/1//237/onto.rdf#" uri="OAEI2016Benchmark/237/onto.rdf"/>
        <uri id="Automatically generated entry, Timestamp=1550131619357" name="http://oaei.ontologymatching.org/2016benchmarks/biblio/1//238/onto.rdf#" uri="OAEI2016Benchmark/238/onto.rdf"/>
        <uri id="Automatically generated entry, Timestamp=1550131619357" name="http://oaei.ontologymatching.org/2016benchmarks/biblio/1//239/onto.rdf#" uri="OAEI2016Benchmark/239/onto.rdf"/>
        <uri id="Automatically generated entry, Timestamp=1550131619357" name="http://oaei.ontologymatching.org/2016benchmarks/biblio/1//240/onto.rdf#" uri="OAEI2016Benchmark/240/onto.rdf"/>
        <uri id="Automatically generated entry, Timestamp=1550131619357" name="http://oaei.ontologymatching.org/2016benchmarks/biblio/1//241/onto.rdf#" uri="OAEI2016Benchmark/241/onto.rdf"/>
        <uri id="Automatically generated entry, Timestamp=1550131619357" name="http://oaei.ontologymatching.org/2016benchmarks/biblio/1//246/onto.rdf#" uri="OAEI2016Benchmark/246/onto.rdf"/>
        <uri id="Automatically generated entry, Timestamp=1550131619357" name="http://oaei.ontologymatching.org/2016benchmarks/biblio/1//247/onto.rdf#" uri="OAEI2016Benchmark/247/onto.rdf"/>
        <uri id="Automatically generated entry, Timestamp=1550131619357" name="http://oaei.ontologymatching.org/2016benchmarks/biblio/1//248-2/onto.rdf#" uri="OAEI2016Benchmark/248-2/onto.rdf"/>
        <uri id="Automatically generated entry, Timestamp=1550131619357" name="http://oaei.ontologymatching.org/2016benchmarks/biblio/1//248-4/onto.rdf#" uri="OAEI2016Benchmark/248-4/onto.rdf"/>
        <uri id="Automatically generated entry, Timestamp=1550131619357" name="http://oaei.ontologymatching.org/2016benchmarks/biblio/1//248-6/onto.rdf#" uri="OAEI2016Benchmark/248-6/onto.rdf"/>
        <uri id="Automatically generated entry, Timestamp=1550131619357" name="http://oaei.ontologymatching.org/2016benchmarks/biblio/1//248-8/onto.rdf#" uri="OAEI2016Benchmark/248-8/onto.rdf"/>
        <uri id="Automatically generated entry, Timestamp=1550131619357" name="http://oaei.ontologymatching.org/2016benchmarks/biblio/1//248/onto.rdf#" uri="OAEI2016Benchmark/248/onto.rdf"/>
        <uri id="Automatically generated entry, Timestamp=1550131619357" name="http://oaei.ontologymatching.org/2016benchmarks/biblio/1//249-2/onto.rdf#" uri="OAEI2016Benchmark/249-2/onto.rdf"/>
        <uri id="Automatically generated entry, Timestamp=1550131619357" name="http://oaei.ontologymatching.org/2016benchmarks/biblio/1//249-4/onto.rdf#" uri="OAEI2016Benchmark/249-4/onto.rdf"/>
        <uri id="Automatically generated entry, Timestamp=1550131619357" name="http://oaei.ontologymatching.org/2016benchmarks/biblio/1//249-6/onto.rdf#" uri="OAEI2016Benchmark/249-6/onto.rdf"/>
        <uri id="Automatically generated entry, Timestamp=1550131619357" name="http://oaei.ontologymatching.org/2016benchmarks/biblio/1//249-8/onto.rdf#" uri="OAEI2016Benchmark/249-8/onto.rdf"/>
        <uri id="Automatically generated entry, Timestamp=1550131619357" name="http://oaei.ontologymatching.org/2016benchmarks/biblio/1//249/onto.rdf#" uri="OAEI2016Benchmark/249/onto.rdf"/>
        <uri id="Automatically generated entry, Timestamp=1550131619357" name="http://oaei.ontologymatching.org/2016benchmarks/biblio/1//250-2/onto.rdf#" uri="OAEI2016Benchmark/250-2/onto.rdf"/>
        <uri id="Automatically generated entry, Timestamp=1550131619357" name="http://oaei.ontologymatching.org/2016benchmarks/biblio/1//250-4/onto.rdf#" uri="OAEI2016Benchmark/250-4/onto.rdf"/>
        <uri id="Automatically generated entry, Timestamp=1550131619357" name="http://oaei.ontologymatching.org/2016benchmarks/biblio/1//250-6/onto.rdf#" uri="OAEI2016Benchmark/250-6/onto.rdf"/>
        <uri id="Automatically generated entry, Timestamp=1550131619357" name="http://oaei.ontologymatching.org/2016benchmarks/biblio/1//250-8/onto.rdf#" uri="OAEI2016Benchmark/250-8/onto.rdf"/>
        <uri id="Automatically generated entry, Timestamp=1550131619357" name="http://oaei.ontologymatching.org/2016benchmarks/biblio/1//250/onto.rdf#" uri="OAEI2016Benchmark/250/onto.rdf"/>
        <uri id="Automatically generated entry, Timestamp=1550131619357" name="http://oaei.ontologymatching.org/2016benchmarks/biblio/1//251-2/onto.rdf#" uri="OAEI2016Benchmark/251-2/onto.rdf"/>
        <uri id="Automatically generated entry, Timestamp=1550131619357" name="http://oaei.ontologymatching.org/2016benchmarks/biblio/1//251-4/onto.rdf#" uri="OAEI2016Benchmark/251-4/onto.rdf"/>
        <uri id="Automatically generated entry, Timestamp=1550131619357" name="http://oaei.ontologymatching.org/2016benchmarks/biblio/1//251-6/onto.rdf#" uri="OAEI2016Benchmark/251-6/onto.rdf"/>
        <uri id="Automatically generated entry, Timestamp=1550131619357" name="http://oaei.ontologymatching.org/2016benchmarks/biblio/1//251-8/onto.rdf#" uri="OAEI2016Benchmark/251-8/onto.rdf"/>
        <uri id="Automatically generated entry, Timestamp=1550131619357" name="http://oaei.ontologymatching.org/2016benchmarks/biblio/1//251/onto.rdf#" uri="OAEI2016Benchmark/251/onto.rdf"/>
        <uri id="Automatically generated entry, Timestamp=1550131619357" name="http://oaei.ontologymatching.org/2016benchmarks/biblio/1//252-2/onto.rdf#" uri="OAEI2016Benchmark/252-2/onto.rdf"/>
        <uri id="Automatically generated entry, Timestamp=1550131619357" name="http://oaei.ontologymatching.org/2016benchmarks/biblio/1//252-4/onto.rdf#" uri="OAEI2016Benchmark/252-4/onto.rdf"/>
        <uri id="Automatically generated entry, Timestamp=1550131619357" name="http://oaei.ontologymatching.org/2016benchmarks/biblio/1//252-6/onto.rdf#" uri="OAEI2016Benchmark/252-6/onto.rdf"/>
        <uri id="Automatically generated entry, Timestamp=1550131619357" name="http://oaei.ontologymatching.org/2016benchmarks/biblio/1//252-8/onto.rdf#" uri="OAEI2016Benchmark/252-8/onto.rdf"/>
        <uri id="Automatically generated entry, Timestamp=1550131619357" name="http://oaei.ontologymatching.org/2016benchmarks/biblio/1//252/onto.rdf#" uri="OAEI2016Benchmark/252/onto.rdf"/>
        <uri id="Automatically generated entry, Timestamp=1550131619357" name="http://oaei.ontologymatching.org/2016benchmarks/biblio/1//253-2/onto.rdf#" uri="OAEI2016Benchmark/253-2/onto.rdf"/>
        <uri id="Automatically generated entry, Timestamp=1550131619357" name="http://oaei.ontologymatching.org/2016benchmarks/biblio/1//253-4/onto.rdf#" uri="OAEI2016Benchmark/253-4/onto.rdf"/>
        <uri id="Automatically generated entry, Timestamp=1550131619357" name="http://oaei.ontologymatching.org/2016benchmarks/biblio/1//253-6/onto.rdf#" uri="OAEI2016Benchmark/253-6/onto.rdf"/>
        <uri id="Automatically generated entry, Timestamp=1550131619357" name="http://oaei.ontologymatching.org/2016benchmarks/biblio/1//253-8/onto.rdf#" uri="OAEI2016Benchmark/253-8/onto.rdf"/>
        <uri id="Automatically generated entry, Timestamp=1550131619357" name="http://oaei.ontologymatching.org/2016benchmarks/biblio/1//253/onto.rdf#" uri="OAEI2016Benchmark/253/onto.rdf"/>
        <uri id="Automatically generated entry, Timestamp=1550131619357" name="http://oaei.ontologymatching.org/2016benchmarks/biblio/1//254-2/onto.rdf#" uri="OAEI2016Benchmark/254-2/onto.rdf"/>
        <uri id="Automatically generated entry, Timestamp=1550131619357" name="http://oaei.ontologymatching.org/2016benchmarks/biblio/1//254-4/onto.rdf#" uri="OAEI2016Benchmark/254-4/onto.rdf"/>
        <uri id="Automatically generated entry, Timestamp=1550131619357" name="http://oaei.ontologymatching.org/2016benchmarks/biblio/1//254-6/onto.rdf#" uri="OAEI2016Benchmark/254-6/onto.rdf"/>
        <uri id="Automatically generated entry, Timestamp=1550131619357" name="http://oaei.ontologymatching.org/2016benchmarks/biblio/1//254-8/onto.rdf#" uri="OAEI2016Benchmark/254-8/onto.rdf"/>
        <uri id="Automatically generated entry, Timestamp=1550131619357" name="http://oaei.ontologymatching.org/2016benchmarks/biblio/1//254/onto.rdf#" uri="OAEI2016Benchmark/254/onto.rdf"/>
        <uri id="Automatically generated entry, Timestamp=1550131619357" name="http://oaei.ontologymatching.org/2016benchmarks/biblio/1//257-2/onto.rdf#" uri="OAEI2016Benchmark/257-2/onto.rdf"/>
        <uri id="Automatically generated entry, Timestamp=1550131619357" name="http://oaei.ontologymatching.org/2016benchmarks/biblio/1//257-4/onto.rdf#" uri="OAEI2016Benchmark/257-4/onto.rdf"/>
        <uri id="Automatically generated entry, Timestamp=1550131619357" name="http://oaei.ontologymatching.org/2016benchmarks/biblio/1//257-6/onto.rdf#" uri="OAEI2016Benchmark/257-6/onto.rdf"/>
        <uri id="Automatically generated entry, Timestamp=1550131619357" name="http://oaei.ontologymatching.org/2016benchmarks/biblio/1//257-8/onto.rdf#" uri="OAEI2016Benchmark/257-8/onto.rdf"/>
        <uri id="Automatically generated entry, Timestamp=1550131619357" name="http://oaei.ontologymatching.org/2016benchmarks/biblio/1//257/onto.rdf#" uri="OAEI2016Benchmark/257/onto.rdf"/>
        <uri id="Automatically generated entry, Timestamp=1550131619357" name="http://oaei.ontologymatching.org/2016benchmarks/biblio/1//258-2/onto.rdf#" uri="OAEI2016Benchmark/258-2/onto.rdf"/>
        <uri id="Automatically generated entry, Timestamp=1550131619357" name="http://oaei.ontologymatching.org/2016benchmarks/biblio/1//258-4/onto.rdf#" uri="OAEI2016Benchmark/258-4/onto.rdf"/>
        <uri id="Automatically generated entry, Timestamp=1550131619357" name="http://oaei.ontologymatching.org/2016benchmarks/biblio/1//258-6/onto.rdf#" uri="OAEI2016Benchmark/258-6/onto.rdf"/>
        <uri id="Automatically generated entry, Timestamp=1550131619357" name="http://oaei.ontologymatching.org/2016benchmarks/biblio/1//258-8/onto.rdf#" uri="OAEI2016Benchmark/258-8/onto.rdf"/>
        <uri id="Automatically generated entry, Timestamp=1550131619357" name="http://oaei.ontologymatching.org/2016benchmarks/biblio/1//258/onto.rdf#" uri="OAEI2016Benchmark/258/onto.rdf"/>
        <uri id="Automatically generated entry, Timestamp=1550131619357" name="http://oaei.ontologymatching.org/2016benchmarks/biblio/1//259-2/onto.rdf#" uri="OAEI2016Benchmark/259-2/onto.rdf"/>
        <uri id="Automatically generated entry, Timestamp=1550131619357" name="http://oaei.ontologymatching.org/2016benchmarks/biblio/1//259-4/onto.rdf#" uri="OAEI2016Benchmark/259-4/onto.rdf"/>
        <uri id="Automatically generated entry, Timestamp=1550131619357" name="http://oaei.ontologymatching.org/2016benchmarks/biblio/1//259-6/onto.rdf#" uri="OAEI2016Benchmark/259-6/onto.rdf"/>
        <uri id="Automatically generated entry, Timestamp=1550131619357" name="http://oaei.ontologymatching.org/2016benchmarks/biblio/1//259-8/onto.rdf#" uri="OAEI2016Benchmark/259-8/onto.rdf"/>
        <uri id="Automatically generated entry, Timestamp=1550131619357" name="http://oaei.ontologymatching.org/2016benchmarks/biblio/1//259/onto.rdf#" uri="OAEI2016Benchmark/259/onto.rdf"/>
        <uri id="Automatically generated entry, Timestamp=1550131619357" name="http://oaei.ontologymatching.org/2016benchmarks/biblio/1//260-2/onto.rdf#" uri="OAEI2016Benchmark/260-2/onto.rdf"/>
        <uri id="Automatically generated entry, Timestamp=1550131619357" name="http://oaei.ontologymatching.org/2016benchmarks/biblio/1//260-4/onto.rdf#" uri="OAEI2016Benchmark/260-4/onto.rdf"/>
        <uri id="Automatically generated entry, Timestamp=1550131619357" name="http://oaei.ontologymatching.org/2016benchmarks/biblio/1//260-6/onto.rdf#" uri="OAEI2016Benchmark/260-6/onto.rdf"/>
        <uri id="Automatically generated entry, Timestamp=1550131619357" name="http://oaei.ontologymatching.org/2016benchmarks/biblio/1//260-8/onto.rdf#" uri="OAEI2016Benchmark/260-8/onto.rdf"/>
        <uri id="Automatically generated entry, Timestamp=1550131619357" name="http://oaei.ontologymatching.org/2016benchmarks/biblio/1//260/onto.rdf#" uri="OAEI2016Benchmark/260/onto.rdf"/>
        <uri id="Automatically generated entry, Timestamp=1550131619357" name="http://oaei.ontologymatching.org/2016benchmarks/biblio/1//261-2/onto.rdf#" uri="OAEI2016Benchmark/261-2/onto.rdf"/>
        <uri id="Automatically generated entry, Timestamp=1550131619357" name="http://oaei.ontologymatching.org/2016benchmarks/biblio/1//261-4/onto.rdf#" uri="OAEI2016Benchmark/261-4/onto.rdf"/>
        <uri id="Automatically generated entry, Timestamp=1550131619357" name="http://oaei.ontologymatching.org/2016benchmarks/biblio/1//261-6/onto.rdf#" uri="OAEI2016Benchmark/261-6/onto.rdf"/>
        <uri id="Automatically generated entry, Timestamp=1550131619357" name="http://oaei.ontologymatching.org/2016benchmarks/biblio/1//261-8/onto.rdf#" uri="OAEI2016Benchmark/261-8/onto.rdf"/>
        <uri id="Automatically generated entry, Timestamp=1550131619357" name="http://oaei.ontologymatching.org/2016benchmarks/biblio/1//261/onto.rdf#" uri="OAEI2016Benchmark/261/onto.rdf"/>
        <uri id="Automatically generated entry, Timestamp=1550131619357" name="http://oaei.ontologymatching.org/2016benchmarks/biblio/1//262-2/onto.rdf#" uri="OAEI2016Benchmark/262-2/onto.rdf"/>
        <uri id="Automatically generated entry, Timestamp=1550131619357" name="http://oaei.ontologymatching.org/2016benchmarks/biblio/1//262-4/onto.rdf#" uri="OAEI2016Benchmark/262-4/onto.rdf"/>
        <uri id="Automatically generated entry, Timestamp=1550131619357" name="http://oaei.ontologymatching.org/2016benchmarks/biblio/1//262-6/onto.rdf#" uri="OAEI2016Benchmark/262-6/onto.rdf"/>
        <uri id="Automatically generated entry, Timestamp=1550131619357" name="http://oaei.ontologymatching.org/2016benchmarks/biblio/1//262-8/onto.rdf#" uri="OAEI2016Benchmark/262-8/onto.rdf"/>
        <uri id="Automatically generated entry, Timestamp=1550131619357" name="http://oaei.ontologymatching.org/2016benchmarks/biblio/1//262/onto.rdf#" uri="OAEI2016Benchmark/262/onto.rdf"/>
        <uri id="Automatically generated entry, Timestamp=1550131619357" name="http://oaei.ontologymatching.org/2016benchmarks/biblio/1//265/onto.rdf#" uri="OAEI2016Benchmark/265/onto.rdf"/>
        <uri id="Automatically generated entry, Timestamp=1550131619357" name="http://oaei.ontologymatching.org/2016benchmarks/biblio/1//266/onto.rdf#" uri="OAEI2016Benchmark/266/onto.rdf"/>
        <uri id="Automatically generated entry, Timestamp=1550131619357" name="http://oaei.ontologymatching.org/tests/101/onto.rdf#" uri="ontologies/Biblio_2015.rdf"/>
        <uri id="Automatically generated entry, Timestamp=1550131619357" name="duplicate:http://oms.omwg.org/wine-vin/" uri="omwg/wine.xml"/>
        <uri id="Automatically generated entry, Timestamp=1550131619357" name="duplicate:http://oms.omwg.org/wine-vin/" uri="omwg/total.xml"/>
        <uri id="Automatically generated entry, Timestamp=1550131619357" name="duplicate:http://oms.omwg.org/wine-vin/" uri="omwg/total-owlable.xml"/>
        <uri id="Automatically generated entry, Timestamp=1550131619357" name="http://project-best.eu/owl/iwxxm-mod/metar" uri="KEOD/datasets_refined/d3/ontologies/iwxxm_metar.owl"/>
        <uri id="Automatically generated entry, Timestamp=1550131619357" name="http://purl.obolibrary.org/obo/envo.owl" uri="ESWC_ATMONTO_AIRM/envo.owl"/>
        <uri id="Automatically generated entry, Timestamp=1550131619357" name="http://purl.org/ontology/bibo/" uri="ontologies/BIBO.owl"/>
        <uri id="Automatically generated entry, Timestamp=1550131619357" name="http://purl.org/td/transportdisruption" uri="transportdisruption.owl"/>
        <uri id="Automatically generated entry, Timestamp=1550131619357" name="http://schema.org" uri="schema-org.owl"/>
        <uri id="Automatically generated entry, Timestamp=1550131619357" name="http://sigkdd" uri="OAEI-16-conference/ontologies/sigkdd.owl"/>
        <uri id="Automatically generated entry, Timestamp=1550131619357" name="http://www.aifb.uni-karlsruhe.de/ontology" uri="ER2017/302303/303.rdf"/>
        <uri id="Automatically generated entry, Timestamp=1550131619357" name="http://www.best-project.org/owl/AIRM" uri="NASA2AIRM/airm-mono.owl"/>
        <uri id="Automatically generated entry, Timestamp=1550131619357" name="http://www.disit.org/km4city/schema" uri="ntnu-lyon-paper/ontologies/km4c.owl"/>
        <uri id="Automatically generated entry, Timestamp=1550131619357" name="http://www.movieontology.org/2009/11/09/movieontology.owl" uri="wndomainsexperiment/movieontology_new.owl"/>
        <uri id="Automatically generated entry, Timestamp=1550131619357" name="http://www.pms.ifi.uni-muenchen.de/OTN" uri="otn.owl"/>
        <uri id="Automatically generated entry, Timestamp=1550131619357" name="http://www.project-best.eu/owl/airm-mod/aerodromeinfrastructure.owl" uri="KEOD/datasets_refined/d1/ontologies/aerodromeinfrastructure.owl"/>
        <uri id="Automatically generated entry, Timestamp=1550131619357" name="http://www.project-best.eu/owl/aixm" uri="KEOD/datasets_refined/d5/ontologies/aixm_geometry.owl"/>
        <uri id="Automatically generated entry, Timestamp=1550131619357" name="http://www.project-best.eu/owl/aixm-mod/airportheliport" uri="KEOD/datasets_refined/d1/ontologies/aixm_airportheliport.owl"/>
        <uri id="Automatically generated entry, Timestamp=1550131619357" name="http://www.project-best.eu/owl/iwxxm-mod/common" uri="KEOD/datasets_refined/d2/ontologies/iwxxm_common.owl"/>
        <uri id="Automatically generated entry, Timestamp=1550131619357" name="http://www.semanticweb.org/audunvennesland/ontologies/2016/11/untitled-ontology-228" uri="ontologies/Test/Animal_1.owl"/>
        <uri id="Automatically generated entry, Timestamp=1550131619357" name="http://www.semanticweb.org/audunvennesland/ontologies/2016/11/untitled-ontology-229" uri="ontologies/Test/Animal_2.owl"/>
        <uri id="Automatically generated entry, Timestamp=1550131619357" name="http://www.semanticweb.org/audunvennesland/ontologies/2016/8/untitled-ontology-199" uri="ontologies/Test/TestTransportWithInstances1.owl"/>
        <uri id="Automatically generated entry, Timestamp=1550131619357" name="http://www.semanticweb.org/audunvennesland/ontologies/2016/8/untitled-ontology-200" uri="ontologies/Test/TestTransportWithInstances2.owl"/>
        <uri id="Automatically generated entry, Timestamp=1550131619357" name="duplicate:http://www.semanticweb.org/audunvennesland/ontologies/2017/1/MusicOntologyMerged2" uri="ntnu-lyon-paper/ontologies/MusicOntologyMerged.owl"/>
        <uri id="Automatically generated entry, Timestamp=1550131619357" name="duplicate:http://www.semanticweb.org/audunvennesland/ontologies/2017/1/MusicOntologyMerged2" uri="ntnu-lyon-paper/ontologies/MusicOntologyMerged.rdf"/>
        <uri id="Automatically generated entry, Timestamp=1550131619357" name="http://www.semanticweb.org/audunvennesland/ontologies/2017/2/TransportDisruptionMergedByProtege" uri="ntnu-lyon-paper/ontologies/td.owl"/>
        <uri id="Automatically generated entry, Timestamp=1550131619357" name="duplicate:http://www.semanticweb.org/audunvennesland/ontologies/2017/7/untitled-ontology-365" uri="Path/PathMatcher2.owl"/>
        <uri id="Automatically generated entry, Timestamp=1550131619357" name="duplicate:http://www.semanticweb.org/audunvennesland/ontologies/2017/7/untitled-ontology-365" uri="Path/PathMatcher1.owl"/>
        <uri id="Automatically generated entry, Timestamp=1550131619357" name="duplicate:http://www.semanticweb.org/audunvennesland/ontologies/2017/7/untitled-ontology-369" uri="Transport/1-owl.owl"/>
        <uri id="Automatically generated entry, Timestamp=1550131619357" name="duplicate:http://www.semanticweb.org/audunvennesland/ontologies/2017/7/untitled-ontology-369" uri="Transport/2-owl.owl"/>
        <uri id="Automatically generated entry, Timestamp=1550131619357" name="duplicate:http://www.semanticweb.org/audunvennesland/ontologies/2017/7/untitled-ontology-369" uri="Transport/2.owl"/>
        <uri id="Automatically generated entry, Timestamp=1550131619357" name="http://www.semanticweb.org/audunvennesland/ontologies/2017/7/untitled-ontology-370" uri="Path/1.owl"/>
        <uri id="Automatically generated entry, Timestamp=1550131619357" name="http://www.semanticweb.org/audunvennesland/ontologies/2018/10/sweetmerged" uri="ESWC_ATMONTO_AIRM/SWEET_MERGED.owl"/>
        <uri id="Automatically generated entry, Timestamp=1550131619357" name="http://www.semanticweb.org/audunvennesland/ontologies/2019/0/untitled-ontology-186" uri="onto1.owl"/>
        <uri id="Automatically generated entry, Timestamp=1550131619357" name="http://www.semanticweb.org/audunvennesland/ontologies/2019/0/untitled-ontology-187" uri="onto2.owl"/>
        <uri id="Automatically generated entry, Timestamp=1550131619357" name="http://www.semanticweb.org/audunvennesland/ontologies/2019/0/untitled-ontology-198" uri="_PHD_EVALUATION/MATCHERTESTING/Vehicle.owl"/>
        <uri id="Automatically generated entry, Timestamp=1550131619357" name="http://www.semanticweb.org/audunvennesland/ontologies/2019/0/untitled-ontology-203" uri="_PHD_EVALUATION/ATMONTO-AIRM/ONTOLOGIES/MergeATMONTO-AIRM.owl"/>
        <uri id="Automatically generated entry, Timestamp=1550131619357" name="http://www.semanticweb.org/audunvennesland/ontologies/2019/0/untitled-ontology-206" uri="_PHD_EVALUATION/BIBFRAME-SCHEMAORG/ONTOLOGIES/MergeBibframe-Schemaorg.owl"/>
        <uri id="Automatically generated entry, Timestamp=1550131619357" name="http://www.semanticweb.org/audunvennesland/ontologies/2019/0/untitled-ontology-212" uri="ConferenceOntology1.owl"/>
        <uri id="Automatically generated entry, Timestamp=1550131619357" name="http://www.semanticweb.org/audunvennesland/ontologies/2019/0/untitled-ontology-214" uri="ConferenceOntology2.owl"/>
        <uri id="Automatically generated entry, Timestamp=1550131619357" name="http://www.semanticweb.org/audunvennesland/ontologies/2019/1/untitled-ontology-219" uri="SATest1.owl"/>
        <uri id="Automatically generated entry, Timestamp=1550131619357" name="http://www.semanticweb.org/audunvennesland/ontologies/2019/1/untitled-ontology-220" uri="SATest2.owl"/>
        <uri id="Automatically generated entry, Timestamp=1550131619357" name="http://www.w3.org/2002/07/owl" uri="ESWC_ATMONTO_AIRM/sweet.owl"/>
        <uri id="Automatically generated entry, Timestamp=1550131619357" name="http://www.w3.org/2002/07/owl#" uri="UoA/yago.owl"/>
        <uri id="Automatically generated entry, Timestamp=1550131619357" name="http://www.w3.org/TR/2003/PR-owl-guide-20031209/wine#" uri="OAEI2009/102/onto.rdf"/>
        <uri id="Automatically generated entry, Timestamp=1550131619357" name="https://data.nasa.gov/ontologies/atmonto/ATM" uri="ESWC_ATMONTO_AIRM/ATMOntoCoreMerged.owl"/>
        <uri id="Automatically generated entry, Timestamp=1550131619357" name="https://data.nasa.gov/ontologies/atmontoCore" uri="NASA2AIRM/atmontoCore.rdf"/>
        <uri id="Automatically generated entry, Timestamp=1550131619357" name="shadowed:http://cmt" uri="experiment_eswc17/ontologies/cmt.owl"/>
        <uri id="Automatically generated entry, Timestamp=1550131619357" name="shadowed:http://confOf" uri="experiment_eswc17/ontologies/confOf.owl"/>
        <uri id="Automatically generated entry, Timestamp=1550131619357" name="shadowed:http://conference" uri="OAEI-16-conference/ontologies/Conference.owl"/>
        <uri id="Automatically generated entry, Timestamp=1550131619357" name="shadowed:http://conference" uri="ntnu-lyon-paper/ontologies/conference.owl"/>
        <uri id="Automatically generated entry, Timestamp=1550131619357" name="shadowed:http://conference" uri="experiment_eswc17/ontologies/conference.owl"/>
        <uri id="Automatically generated entry, Timestamp=1550131619357" name="shadowed:http://conference" uri="alignmentCombiner/conference-ekaw/Conference.owl"/>
        <uri id="Automatically generated entry, Timestamp=1550131619357" name="shadowed:http://ebiquity.umbc.edu/v2.1/ontology/publication.owl" uri="ER2017/302304/302.rdf"/>
        <uri id="Automatically generated entry, Timestamp=1550131619357" name="shadowed:http://ebiquity.umbc.edu/v2.1/ontology/publication.owl" uri="ER2017/301302/302.rdf"/>
        <uri id="Automatically generated entry, Timestamp=1550131619357" name="shadowed:http://ebiquity.umbc.edu/v2.1/ontology/publication.owl" uri="wordembedding/302303/302303-302.rdf"/>
        <uri id="Automatically generated entry, Timestamp=1550131619357" name="shadowed:http://ebiquity.umbc.edu/v2.1/ontology/publication.owl" uri="wordembedding/302304/302304-302.rdf"/>
        <uri id="Automatically generated entry, Timestamp=1550131619357" name="shadowed:http://ebiquity.umbc.edu/v2.1/ontology/publication.owl" uri="wordembedding/301302/301302-302.rdf"/>
        <uri id="Automatically generated entry, Timestamp=1550131619357" name="shadowed:http://ebiquity.umbc.edu/v2.1/ontology/publication.owl" uri="OAEI2011/302-303/302.rdf"/>
        <uri id="Automatically generated entry, Timestamp=1550131619357" name="shadowed:http://ebiquity.umbc.edu/v2.1/ontology/publication.owl" uri="OAEI2011/301-302/302.rdf"/>
        <uri id="Automatically generated entry, Timestamp=1550131619357" name="shadowed:http://ebiquity.umbc.edu/v2.1/ontology/publication.owl" uri="OAEI2011/302-304/302.rdf"/>
        <uri id="Automatically generated entry, Timestamp=1550131619357" name="shadowed:http://ebiquity.umbc.edu/v2.1/ontology/publication.owl" uri="ESWC_WordEmbedding_Experiment/OAEI2011/ontologies/302303/302303-302.rdf"/>
        <uri id="Automatically generated entry, Timestamp=1550131619357" name="shadowed:http://ebiquity.umbc.edu/v2.1/ontology/publication.owl" uri="ESWC_WordEmbedding_Experiment/OAEI2011/ontologies/301302/301302-302.rdf"/>
        <uri id="Automatically generated entry, Timestamp=1550131619357" name="shadowed:http://ebiquity.umbc.edu/v2.1/ontology/publication.owl" uri="ESWC_WordEmbedding_Experiment/OAEI2011/ontologies/302304/302304-302.rdf"/>
        <uri id="Automatically generated entry, Timestamp=1550131619357" name="shadowed:http://ebiquity.umbc.edu/v2.1/ontology/publication.owl" uri="ESWC_WordEmbedding_Experiment/OAEI2011/coma/ontologies/301302/301302-302.rdf"/>
        <uri id="Automatically generated entry, Timestamp=1550131619357" name="shadowed:http://ebiquity.umbc.edu/v2.1/ontology/publication.owl" uri="ESWC_WordEmbedding_Experiment/OAEI2011/coma/ontologies/302304/302304-302.rdf"/>
        <uri id="Automatically generated entry, Timestamp=1550131619357" name="shadowed:http://ebiquity.umbc.edu/v2.1/ontology/publication.owl" uri="ESWC_WordEmbedding_Experiment/OAEI2011/coma/ontologies/302303/302303-302.rdf"/>
        <uri id="Automatically generated entry, Timestamp=1550131619357" name="shadowed:http://ebiquity.umbc.edu/v2.1/ontology/publication.owl" uri="ESWC_WordEmbedding_Experiment/OAEI2011/smatch/ontologies/302304/302304-302.rdf"/>
        <uri id="Automatically generated entry, Timestamp=1550131619357" name="shadowed:http://ebiquity.umbc.edu/v2.1/ontology/publication.owl" uri="ESWC_WordEmbedding_Experiment/OAEI2011/smatch/ontologies/302303/302303-302.rdf"/>
        <uri id="Automatically generated entry, Timestamp=1550131619357" name="shadowed:http://ebiquity.umbc.edu/v2.1/ontology/publication.owl" uri="ESWC_WordEmbedding_Experiment/OAEI2011/smatch/ontologies/301302/301302-302.rdf"/>
        <uri id="Automatically generated entry, Timestamp=1550131619357" name="shadowed:http://ebiquity.umbc.edu/v2.1/ontology/publication.owl" uri="_PHD_EVALUATION/OAEI2011/ONTOLOGIES/302303/302303-302.rdf"/>
        <uri id="Automatically generated entry, Timestamp=1550131619357" name="shadowed:http://ebiquity.umbc.edu/v2.1/ontology/publication.owl" uri="_PHD_EVALUATION/OAEI2011/ONTOLOGIES/302304/302304-302.rdf"/>
        <uri id="Automatically generated entry, Timestamp=1550131619357" name="shadowed:http://ebiquity.umbc.edu/v2.1/ontology/publication.owl" uri="_PHD_EVALUATION/OAEI2011/ONTOLOGIES/301302/301302-302.rdf"/>
        <uri id="Automatically generated entry, Timestamp=1550131619357" name="shadowed:http://ebiquity.umbc.edu/v2.1/ontology/publication.owl#" uri="OAEI2009/allontologies/302.rdf"/>
        <uri id="Automatically generated entry, Timestamp=1550131619357" name="shadowed:http://ekaw" uri="OAEI-16-conference/ontologies/ekaw.owl"/>
        <uri id="Automatically generated entry, Timestamp=1550131619357" name="shadowed:http://ekaw" uri="ntnu-lyon-paper/ontologies/ekaw.owl"/>
        <uri id="Automatically generated entry, Timestamp=1550131619357" name="shadowed:http://ekaw" uri="experiment_eswc17/ontologies/ekaw.owl"/>
        <uri id="Automatically generated entry, Timestamp=1550131619357" name="shadowed:http://ekaw" uri="alignmentCombiner/conference-ekaw/ekaw.owl"/>
        <uri id="Automatically generated entry, Timestamp=1550131619357" name="shadowed:http://id.loc.gov/ontologies/bibframe/" uri="_PHD_EVALUATION/BIBFRAME-SCHEMAORG/ONTOLOGIES/bibframe.owl"/>
        <uri id="Automatically generated entry, Timestamp=1550131619357" name="shadowed:http://id.loc.gov/ontologies/bibframe/" uri="_PHD_EVALUATION/BIBFRAME-SCHEMAORG/ONTOLOGIES/bibframe.rdf"/>
        <uri id="Automatically generated entry, Timestamp=1550131619357" name="shadowed:http://id.loc.gov/ontologies/bibframe/" uri="wndomainsexperiment/bibframe.rdf"/>
        <uri id="Automatically generated entry, Timestamp=1550131619357" name="shadowed:http://oaei.ontologymatching.org/2006/benchmarks/103/onto.rdf#" uri="OAEI2009/allontologies/103.rdf"/>
        <uri id="Automatically generated entry, Timestamp=1550131619357" name="shadowed:http://oaei.ontologymatching.org/2006/benchmarks/104/onto.rdf#" uri="OAEI2009/allontologies/104.rdf"/>
        <uri id="Automatically generated entry, Timestamp=1550131619357" name="shadowed:http://oaei.ontologymatching.org/2006/benchmarks/203/onto.rdf#" uri="OAEI2009/allontologies/203.rdf"/>
        <uri id="Automatically generated entry, Timestamp=1550131619357" name="shadowed:http://oaei.ontologymatching.org/2006/benchmarks/204/onto.rdf#" uri="OAEI2009/allontologies/204.rdf"/>
        <uri id="Automatically generated entry, Timestamp=1550131619357" name="shadowed:http://oaei.ontologymatching.org/2006/benchmarks/205/onto.rdf#" uri="OAEI2009/allontologies/205.rdf"/>
        <uri id="Automatically generated entry, Timestamp=1550131619357" name="shadowed:http://oaei.ontologymatching.org/2006/benchmarks/207/onto.rdf#" uri="OAEI2009/allontologies/207.rdf"/>
        <uri id="Automatically generated entry, Timestamp=1550131619357" name="shadowed:http://oaei.ontologymatching.org/2006/benchmarks/208/onto.rdf#" uri="OAEI2009/allontologies/208.rdf"/>
        <uri id="Automatically generated entry, Timestamp=1550131619357" name="shadowed:http://oaei.ontologymatching.org/2006/benchmarks/209/onto.rdf#" uri="OAEI2009/allontologies/209.rdf"/>
        <uri id="Automatically generated entry, Timestamp=1550131619357" name="shadowed:http://oaei.ontologymatching.org/2006/benchmarks/210/onto.rdf#" uri="OAEI2009/allontologies/210.rdf"/>
        <uri id="Automatically generated entry, Timestamp=1550131619357" name="shadowed:http://oaei.ontologymatching.org/2006/benchmarks/222/onto.rdf#" uri="OAEI2009/allontologies/222.rdf"/>
        <uri id="Automatically generated entry, Timestamp=1550131619357" name="shadowed:http://oaei.ontologymatching.org/2006/benchmarks/223/onto.rdf#" uri="OAEI2009/allontologies/223.rdf"/>
        <uri id="Automatically generated entry, Timestamp=1550131619357" name="shadowed:http://oaei.ontologymatching.org/2006/benchmarks/224/onto.rdf#" uri="OAEI2009/allontologies/224.rdf"/>
        <uri id="Automatically generated entry, Timestamp=1550131619357" name="shadowed:http://oaei.ontologymatching.org/2006/benchmarks/225/onto.rdf#" uri="OAEI2009/allontologies/225.rdf"/>
        <uri id="Automatically generated entry, Timestamp=1550131619357" name="shadowed:http://oaei.ontologymatching.org/2006/benchmarks/230/onto.rdf#" uri="OAEI2009/allontologies/230.rdf"/>
        <uri id="Automatically generated entry, Timestamp=1550131619357" name="shadowed:http://oaei.ontologymatching.org/2006/benchmarks/231/onto.rdf#" uri="OAEI2009/allontologies/231.rdf"/>
        <uri id="Automatically generated entry, Timestamp=1550131619357" name="shadowed:http://oaei.ontologymatching.org/2006/benchmarks/237/onto.rdf#" uri="OAEI2009/allontologies/237.rdf"/>
        <uri id="Automatically generated entry, Timestamp=1550131619357" name="shadowed:http://oaei.ontologymatching.org/2006/benchmarks/238/onto.rdf#" uri="OAEI2009/allontologies/238.rdf"/>
        <uri id="Automatically generated entry, Timestamp=1550131619357" name="shadowed:http://oaei.ontologymatching.org/2006/benchmarks/301/onto.rdf#" uri="OAEI2009/allontologies/301.rdf"/>
        <uri id="Automatically generated entry, Timestamp=1550131619357" name="shadowed:http://oaei.ontologymatching.org/2006/benchmarks/304/onto.rdf#" uri="OAEI2009/allontologies/304.rdf"/>
        <uri id="Automatically generated entry, Timestamp=1550131619357" name="shadowed:http://oaei.ontologymatching.org/2009/benchmarks/304/onto.rdf" uri="ER2017/302304/304.rdf"/>
        <uri id="Automatically generated entry, Timestamp=1550131619357" name="shadowed:http://oaei.ontologymatching.org/2009/benchmarks/304/onto.rdf" uri="ER2017/301304/304.rdf"/>
        <uri id="Automatically generated entry, Timestamp=1550131619357" name="shadowed:http://oaei.ontologymatching.org/2009/benchmarks/304/onto.rdf" uri="wordembedding/303304/303304-304.rdf"/>
        <uri id="Automatically generated entry, Timestamp=1550131619357" name="shadowed:http://oaei.ontologymatching.org/2009/benchmarks/304/onto.rdf" uri="wordembedding/302304/302304-304.rdf"/>
        <uri id="Automatically generated entry, Timestamp=1550131619357" name="shadowed:http://oaei.ontologymatching.org/2009/benchmarks/304/onto.rdf" uri="wordembedding/301304/301304-304.rdf"/>
        <uri id="Automatically generated entry, Timestamp=1550131619357" name="shadowed:http://oaei.ontologymatching.org/2009/benchmarks/304/onto.rdf" uri="OAEI2011/302-304/304.rdf"/>
        <uri id="Automatically generated entry, Timestamp=1550131619357" name="shadowed:http://oaei.ontologymatching.org/2009/benchmarks/304/onto.rdf" uri="OAEI2011/301-304/304.rdf"/>
        <uri id="Automatically generated entry, Timestamp=1550131619357" name="shadowed:http://oaei.ontologymatching.org/2009/benchmarks/304/onto.rdf" uri="OAEI2011/303-304/304.rdf"/>
        <uri id="Automatically generated entry, Timestamp=1550131619357" name="shadowed:http://oaei.ontologymatching.org/2009/benchmarks/304/onto.rdf" uri="ESWC_WordEmbedding_Experiment/OAEI2011/ontologies/303304/303304-304.rdf"/>
        <uri id="Automatically generated entry, Timestamp=1550131619357" name="shadowed:http://oaei.ontologymatching.org/2009/benchmarks/304/onto.rdf" uri="ESWC_WordEmbedding_Experiment/OAEI2011/ontologies/302304/302304-304.rdf"/>
        <uri id="Automatically generated entry, Timestamp=1550131619357" name="shadowed:http://oaei.ontologymatching.org/2009/benchmarks/304/onto.rdf" uri="ESWC_WordEmbedding_Experiment/OAEI2011/ontologies/301304/301304-304.rdf"/>
        <uri id="Automatically generated entry, Timestamp=1550131619357" name="shadowed:http://oaei.ontologymatching.org/2009/benchmarks/304/onto.rdf" uri="ESWC_WordEmbedding_Experiment/OAEI2011/coma/ontologies/301304/301304-304.rdf"/>
        <uri id="Automatically generated entry, Timestamp=1550131619357" name="shadowed:http://oaei.ontologymatching.org/2009/benchmarks/304/onto.rdf" uri="ESWC_WordEmbedding_Experiment/OAEI2011/coma/ontologies/302304/302304-304.rdf"/>
        <uri id="Automatically generated entry, Timestamp=1550131619357" name="shadowed:http://oaei.ontologymatching.org/2009/benchmarks/304/onto.rdf" uri="ESWC_WordEmbedding_Experiment/OAEI2011/coma/ontologies/303304/303304-304.rdf"/>
        <uri id="Automatically generated entry, Timestamp=1550131619357" name="shadowed:http://oaei.ontologymatching.org/2009/benchmarks/304/onto.rdf" uri="ESWC_WordEmbedding_Experiment/OAEI2011/smatch/ontologies/301304/301304-304.rdf"/>
        <uri id="Automatically generated entry, Timestamp=1550131619357" name="shadowed:http://oaei.ontologymatching.org/2009/benchmarks/304/onto.rdf" uri="ESWC_WordEmbedding_Experiment/OAEI2011/smatch/ontologies/302304/302304-304.rdf"/>
        <uri id="Automatically generated entry, Timestamp=1550131619357" name="shadowed:http://oaei.ontologymatching.org/2009/benchmarks/304/onto.rdf" uri="ESWC_WordEmbedding_Experiment/OAEI2011/smatch/ontologies/303304/303304-304.rdf"/>
        <uri id="Automatically generated entry, Timestamp=1550131619357" name="shadowed:http://oaei.ontologymatching.org/2009/benchmarks/304/onto.rdf" uri="_PHD_EVALUATION/OAEI2011/ONTOLOGIES/303304/303304-304.rdf"/>
        <uri id="Automatically generated entry, Timestamp=1550131619357" name="shadowed:http://oaei.ontologymatching.org/2009/benchmarks/304/onto.rdf" uri="_PHD_EVALUATION/OAEI2011/ONTOLOGIES/302304/302304-304.rdf"/>
        <uri id="Automatically generated entry, Timestamp=1550131619357" name="shadowed:http://oaei.ontologymatching.org/2009/benchmarks/304/onto.rdf" uri="_PHD_EVALUATION/OAEI2011/ONTOLOGIES/301304/301304-304.rdf"/>
        <uri id="Automatically generated entry, Timestamp=1550131619357" name="shadowed:http://oaei.ontologymatching.org/2010/benchmarks/301/onto.rdf" uri="ER2017/301302/301.rdf"/>
        <uri id="Automatically generated entry, Timestamp=1550131619357" name="shadowed:http://oaei.ontologymatching.org/2010/benchmarks/301/onto.rdf" uri="ER2017/301304/301.rdf"/>
        <uri id="Automatically generated entry, Timestamp=1550131619357" name="shadowed:http://oaei.ontologymatching.org/2010/benchmarks/301/onto.rdf" uri="wordembedding/301303/301303-301.rdf"/>
        <uri id="Automatically generated entry, Timestamp=1550131619357" name="shadowed:http://oaei.ontologymatching.org/2010/benchmarks/301/onto.rdf" uri="wordembedding/301302/301302-301.rdf"/>
        <uri id="Automatically generated entry, Timestamp=1550131619357" name="shadowed:http://oaei.ontologymatching.org/2010/benchmarks/301/onto.rdf" uri="wordembedding/301304/301304-301.rdf"/>
        <uri id="Automatically generated entry, Timestamp=1550131619357" name="shadowed:http://oaei.ontologymatching.org/2010/benchmarks/301/onto.rdf" uri="OAEI2011/301-302/301.rdf"/>
        <uri id="Automatically generated entry, Timestamp=1550131619357" name="shadowed:http://oaei.ontologymatching.org/2010/benchmarks/301/onto.rdf" uri="OAEI2011/301-303/301.rdf"/>
        <uri id="Automatically generated entry, Timestamp=1550131619357" name="shadowed:http://oaei.ontologymatching.org/2010/benchmarks/301/onto.rdf" uri="OAEI2011/301-304/301.rdf"/>
        <uri id="Automatically generated entry, Timestamp=1550131619357" name="shadowed:http://oaei.ontologymatching.org/2010/benchmarks/301/onto.rdf" uri="ESWC_WordEmbedding_Experiment/OAEI2011/ontologies/301302/301302-301.rdf"/>
        <uri id="Automatically generated entry, Timestamp=1550131619357" name="shadowed:http://oaei.ontologymatching.org/2010/benchmarks/301/onto.rdf" uri="ESWC_WordEmbedding_Experiment/OAEI2011/ontologies/301303/301303-301.rdf"/>
        <uri id="Automatically generated entry, Timestamp=1550131619357" name="shadowed:http://oaei.ontologymatching.org/2010/benchmarks/301/onto.rdf" uri="ESWC_WordEmbedding_Experiment/OAEI2011/ontologies/301304/301304-301.rdf"/>
        <uri id="Automatically generated entry, Timestamp=1550131619357" name="shadowed:http://oaei.ontologymatching.org/2010/benchmarks/301/onto.rdf" uri="ESWC_WordEmbedding_Experiment/OAEI2011/coma/ontologies/301302/301302-301.rdf"/>
        <uri id="Automatically generated entry, Timestamp=1550131619357" name="shadowed:http://oaei.ontologymatching.org/2010/benchmarks/301/onto.rdf" uri="ESWC_WordEmbedding_Experiment/OAEI2011/coma/ontologies/301303/301303-301.rdf"/>
        <uri id="Automatically generated entry, Timestamp=1550131619357" name="shadowed:http://oaei.ontologymatching.org/2010/benchmarks/301/onto.rdf" uri="ESWC_WordEmbedding_Experiment/OAEI2011/coma/ontologies/301304/301304-301.rdf"/>
        <uri id="Automatically generated entry, Timestamp=1550131619357" name="shadowed:http://oaei.ontologymatching.org/2010/benchmarks/301/onto.rdf" uri="ESWC_WordEmbedding_Experiment/OAEI2011/smatch/ontologies/301304/301304-301.rdf"/>
        <uri id="Automatically generated entry, Timestamp=1550131619357" name="shadowed:http://oaei.ontologymatching.org/2010/benchmarks/301/onto.rdf" uri="ESWC_WordEmbedding_Experiment/OAEI2011/smatch/ontologies/301303/301303-301.rdf"/>
        <uri id="Automatically generated entry, Timestamp=1550131619357" name="shadowed:http://oaei.ontologymatching.org/2010/benchmarks/301/onto.rdf" uri="ESWC_WordEmbedding_Experiment/OAEI2011/smatch/ontologies/301302/301302-301.rdf"/>
        <uri id="Automatically generated entry, Timestamp=1550131619357" name="shadowed:http://oaei.ontologymatching.org/2010/benchmarks/301/onto.rdf" uri="_PHD_EVALUATION/OAEI2011/ONTOLOGIES/301303/301303-301.rdf"/>
        <uri id="Automatically generated entry, Timestamp=1550131619357" name="shadowed:http://oaei.ontologymatching.org/2010/benchmarks/301/onto.rdf" uri="_PHD_EVALUATION/OAEI2011/ONTOLOGIES/301302/301302-301.rdf"/>
        <uri id="Automatically generated entry, Timestamp=1550131619357" name="shadowed:http://oaei.ontologymatching.org/2010/benchmarks/301/onto.rdf" uri="_PHD_EVALUATION/OAEI2011/ONTOLOGIES/301304/301304-301.rdf"/>
        <uri id="Automatically generated entry, Timestamp=1550131619357" name="shadowed:http://oaei.ontologymatching.org/tests/101/onto.rdf#" uri="OAEI-16-conference/ontologies/Biblio_2015.rdf"/>
        <uri id="Automatically generated entry, Timestamp=1550131619357" name="shadowed:http://oaei.ontologymatching.org/tests/101/onto.rdf#" uri="experiment_eswc17/ontologies/biblio.rdf"/>
        <uri id="Automatically generated entry, Timestamp=1550131619357" name="shadowed:http://purl.org/ontology/bibo/" uri="OAEI-16-conference/ontologies/BIBO.owl"/>
        <uri id="Automatically generated entry, Timestamp=1550131619357" name="shadowed:http://purl.org/ontology/bibo/" uri="experiment_eswc17/ontologies/bibo.owl"/>
        <uri id="Automatically generated entry, Timestamp=1550131619357" name="shadowed:http://schema.org" uri="ESWC_ATMONTO_AIRM/schema-org.owl"/>
        <uri id="Automatically generated entry, Timestamp=1550131619357" name="shadowed:http://schema.org" uri="_PHD_EVALUATION/BIBFRAME-SCHEMAORG/ONTOLOGIES/schema-org.owl"/>
        <uri id="Automatically generated entry, Timestamp=1550131619357" name="shadowed:http://schema.org" uri="wndomainsexperiment/schema-org.owl"/>
        <uri id="Automatically generated entry, Timestamp=1550131619357" name="shadowed:http://www.aifb.uni-karlsruhe.de/ontology" uri="ER2017/303304/303.rdf"/>
        <uri id="Automatically generated entry, Timestamp=1550131619357" name="shadowed:http://www.aifb.uni-karlsruhe.de/ontology" uri="ER2017/301303/303.rdf"/>
        <uri id="Automatically generated entry, Timestamp=1550131619357" name="shadowed:http://www.aifb.uni-karlsruhe.de/ontology" uri="wordembedding/302303/302303-303.rdf"/>
        <uri id="Automatically generated entry, Timestamp=1550131619357" name="shadowed:http://www.aifb.uni-karlsruhe.de/ontology" uri="wordembedding/303304/303304-303.rdf"/>
        <uri id="Automatically generated entry, Timestamp=1550131619357" name="shadowed:http://www.aifb.uni-karlsruhe.de/ontology" uri="wordembedding/301303/301303-303.rdf"/>
        <uri id="Automatically generated entry, Timestamp=1550131619357" name="shadowed:http://www.aifb.uni-karlsruhe.de/ontology" uri="OAEI2011/302-303/303.rdf"/>
        <uri id="Automatically generated entry, Timestamp=1550131619357" name="shadowed:http://www.aifb.uni-karlsruhe.de/ontology" uri="OAEI2011/301-303/303.rdf"/>
        <uri id="Automatically generated entry, Timestamp=1550131619357" name="shadowed:http://www.aifb.uni-karlsruhe.de/ontology" uri="OAEI2011/303-304/303.rdf"/>
        <uri id="Automatically generated entry, Timestamp=1550131619357" name="shadowed:http://www.aifb.uni-karlsruhe.de/ontology" uri="ESWC_WordEmbedding_Experiment/OAEI2011/ontologies/303304/303304-303.rdf"/>
        <uri id="Automatically generated entry, Timestamp=1550131619357" name="shadowed:http://www.aifb.uni-karlsruhe.de/ontology" uri="ESWC_WordEmbedding_Experiment/OAEI2011/ontologies/302303/302303-303.rdf"/>
        <uri id="Automatically generated entry, Timestamp=1550131619357" name="shadowed:http://www.aifb.uni-karlsruhe.de/ontology" uri="ESWC_WordEmbedding_Experiment/OAEI2011/ontologies/301303/301303-303.rdf"/>
        <uri id="Automatically generated entry, Timestamp=1550131619357" name="shadowed:http://www.aifb.uni-karlsruhe.de/ontology" uri="ESWC_WordEmbedding_Experiment/OAEI2011/coma/ontologies/301303/301303-303.rdf"/>
        <uri id="Automatically generated entry, Timestamp=1550131619357" name="shadowed:http://www.aifb.uni-karlsruhe.de/ontology" uri="ESWC_WordEmbedding_Experiment/OAEI2011/coma/ontologies/302303/302303-303.rdf"/>
        <uri id="Automatically generated entry, Timestamp=1550131619357" name="shadowed:http://www.aifb.uni-karlsruhe.de/ontology" uri="ESWC_WordEmbedding_Experiment/OAEI2011/coma/ontologies/303304/303304-303.rdf"/>
        <uri id="Automatically generated entry, Timestamp=1550131619357" name="shadowed:http://www.aifb.uni-karlsruhe.de/ontology" uri="ESWC_WordEmbedding_Experiment/OAEI2011/smatch/ontologies/301303/301303-303.rdf"/>
        <uri id="Automatically generated entry, Timestamp=1550131619357" name="shadowed:http://www.aifb.uni-karlsruhe.de/ontology" uri="ESWC_WordEmbedding_Experiment/OAEI2011/smatch/ontologies/302303/302303-303.rdf"/>
        <uri id="Automatically generated entry, Timestamp=1550131619357" name="shadowed:http://www.aifb.uni-karlsruhe.de/ontology" uri="ESWC_WordEmbedding_Experiment/OAEI2011/smatch/ontologies/303304/303304-303.rdf"/>
        <uri id="Automatically generated entry, Timestamp=1550131619357" name="shadowed:http://www.aifb.uni-karlsruhe.de/ontology" uri="_PHD_EVALUATION/OAEI2011/ONTOLOGIES/302303/302303-303.rdf"/>
        <uri id="Automatically generated entry, Timestamp=1550131619357" name="shadowed:http://www.aifb.uni-karlsruhe.de/ontology" uri="_PHD_EVALUATION/OAEI2011/ONTOLOGIES/303304/303304-303.rdf"/>
        <uri id="Automatically generated entry, Timestamp=1550131619357" name="shadowed:http://www.aifb.uni-karlsruhe.de/ontology" uri="_PHD_EVALUATION/OAEI2011/ONTOLOGIES/301303/301303-303.rdf"/>
        <uri id="Automatically generated entry, Timestamp=1550131619357" name="shadowed:http://www.best-project.org/owl/AIRM" uri="ESWC_ATMONTO_AIRM/airm-mono.owl"/>
        <uri id="Automatically generated entry, Timestamp=1550131619357" name="shadowed:http://www.best-project.org/owl/AIRM" uri="ESWC_WordEmbedding_Experiment/ATMONTO-AIRM-O/ontologies/airm-mono.owl"/>
        <uri id="Automatically generated entry, Timestamp=1550131619357" name="shadowed:http://www.best-project.org/owl/AIRM" uri="_PHD_EVALUATION/ATMONTO-AIRM/ONTOLOGIES/airm-mono.owl"/>
        <uri id="Automatically generated entry, Timestamp=1550131619357" name="shadowed:http://www.best-project.org/owl/AIRM" uri="KEOD/datasets_refined/d5/ontologies/airm-mono.owl"/>
        <uri id="Automatically generated entry, Timestamp=1550131619357" name="shadowed:http://www.best-project.org/owl/AIRM" uri="KEOD/datasets_refined/d6/ontologies/airm-mono.owl"/>
        <uri id="Automatically generated entry, Timestamp=1550131619357" name="shadowed:http://www.best-project.org/owl/AIRM" uri="KEOD/datasets_refined/d7/ontologies/airm-mono.owl"/>
        <uri id="Automatically generated entry, Timestamp=1550131619357" name="shadowed:http://www.best-project.org/owl/AIRM" uri="KEOD/datasets_refined/d2/ontologies/airm-mono.owl"/>
        <uri id="Automatically generated entry, Timestamp=1550131619357" name="shadowed:http://www.best-project.org/owl/AIRM" uri="KEOD/datasets_refined/d3/ontologies/airm-mono.owl"/>
        <uri id="Automatically generated entry, Timestamp=1550131619357" name="shadowed:http://www.best-project.org/owl/AIRM" uri="KEOD/datasets_refined/d4/ontologies/airm-mono.owl"/>
        <uri id="Automatically generated entry, Timestamp=1550131619357" name="shadowed:http://www.pms.ifi.uni-muenchen.de/OTN" uri="ntnu-lyon-paper/ontologies/otn.owl"/>
        <uri id="Automatically generated entry, Timestamp=1550131619357" name="shadowed:http://www.project-best.eu/owl/aixm" uri="KEOD/datasets_refined/d6/ontologies/aixm_obstacle.owl"/>
        <uri id="Automatically generated entry, Timestamp=1550131619357" name="shadowed:http://www.project-best.eu/owl/aixm" uri="KEOD/datasets_refined/d7/ontologies/aixm_organisation.owl"/>
        <uri id="Automatically generated entry, Timestamp=1550131619357" name="shadowed:http://www.project-best.eu/owl/aixm" uri="KEOD/datasets_refined/d4/ontologies/aixm_shared.owl"/>
        <uri id="Automatically generated entry, Timestamp=1550131619357" name="shadowed:http://www.semanticweb.org/audunvennesland/ontologies/2016/8/untitled-ontology-199" uri="Transport/TestTransportWithInstances1.owl"/>
        <uri id="Automatically generated entry, Timestamp=1550131619357" name="shadowed:http://www.semanticweb.org/audunvennesland/ontologies/2016/8/untitled-ontology-200" uri="alignmentCombiner/TestTransportWithInstances2.owl"/>
        <uri id="Automatically generated entry, Timestamp=1550131619357" name="shadowed:http://www.semanticweb.org/audunvennesland/ontologies/2017/7/untitled-ontology-369" uri="alignmentCombiner/1-owl.owl"/>
        <uri id="Automatically generated entry, Timestamp=1550131619357" name="shadowed:http://www.semanticweb.org/audunvennesland/ontologies/2017/7/untitled-ontology-369" uri="alignmentCombiner/2.owl"/>
        <uri id="Automatically generated entry, Timestamp=1550131619357" name="shadowed:http://www.semanticweb.org/audunvennesland/ontologies/2017/7/untitled-ontology-370" uri="Transport/1.owl"/>
        <uri id="Automatically generated entry, Timestamp=1550131619357" name="shadowed:http://www.w3.org/2002/07/owl" uri="_PHD_EVALUATION/BIBFRAME-SCHEMAORG/ONTOLOGIES/schema-all-layers.owl"/>
        <uri id="Automatically generated entry, Timestamp=1550131619357" name="shadowed:https://data.nasa.gov/ontologies/atmonto/ATM" uri="ESWC_WordEmbedding_Experiment/ATMONTO-AIRM-O/ontologies/ATMOntoCoreMerged.owl"/>
        <uri id="Automatically generated entry, Timestamp=1550131619357" name="shadowed:https://data.nasa.gov/ontologies/atmonto/ATM" uri="_PHD_EVALUATION/ATMONTO-AIRM/ONTOLOGIES/ATMOntoCoreMerged.owl"/>
    </group>
</catalog>
